<?xml version="1.0" encoding="utf-8" ?>
<ActiveMoveTemplate huntingZoneId="7">
	<ActiveMove id="6600" type="1" pos="0.0000,0.0000,0.0000" skillId="0" distance="0.000000" randomRange="0.000000"/>
	<ActiveMove id="6601" type="1" pos="100.0000,0.0000,0.0000" skillId="0" distance="0.000000" randomRange="25.000000"/>
	<ActiveMove id="6602" type="3" pos="0.0000,0.0000,0.0000" skillId="0" distance="75.000000" randomRange="25.000000"/>
	<ActiveMove id="6603" type="1" pos="0.0000,150.0000,0.0000" skillId="0" distance="0.000000" randomRange="50.000000"/>
	<ActiveMove id="6604" type="1" pos="0.0000,-150.0000,0.0000" skillId="0" distance="0.000000" randomRange="50.000000"/>
	<ActiveMove id="6605" type="1" pos="-1,0.0000,0.0000" skillId="0" distance="0.000000" randomRange="0.000000"/>
	<ActiveMove id="6606" type="1" pos="150,0.0000,0.0000" skillId="0" distance="0.000000" randomRange="25.000000"/>
	<ActiveMove id="6607" type="1" pos="0.0000,150,0.0000" skillId="0" distance="0.000000" randomRange="25.000000"/>
	<ActiveMove id="6608" type="1" pos="0.0000,-150,0.0000" skillId="0" distance="0.000000" randomRange="0.000000"/>
	<ActiveMove id="6609" type="1" pos="100.0000,100.0000,0.0000" skillId="0" distance="0.000000" randomRange="25.000000"/>
	<ActiveMove id="6610" type="1" pos="200.0000,-200.0000,0.0000" skillId="0" distance="0.000000" randomRange="25.000000"/>
	<ActiveMove id="6611" type="3" pos="0.0000,0.0000,0.0000" skillId="0" distance="250.000000" randomRange="25.000000"/>
	<ActiveMove id="6612" type="3" pos="0.0000,0.0000,0.0000" skillId="1150" distance="-200.000000" randomRange="0.000000"/>
	<ActiveMove id="6613" type="3" pos="0.0000,0.0000,0.0000" skillId="2150" distance="-200.000000" randomRange="0.000000"/>
	<ActiveMove id="6614" type="3" pos="0.0000,0.0000,0.0000" skillId="1150" distance="-300.000000" randomRange="0.000000"/>
	<ActiveMove id="6615" type="3" pos="0.0000,0.0000,0.0000" skillId="2150" distance="-300.000000" randomRange="0.000000"/>
	<ActiveMove id="1" type="3" distance="200.000000" randomRange="10.000000" skillId="0"/>
	<ActiveMove id="2" type="1" pos="0,100,0" skillId="0"/>
	<ActiveMove id="3" type="1" pos="0,-100,0" skillId="0"/>
	<ActiveMove id="4" type="1" pos="-200,0,0" skillId="0" distance="0.000000" randomRange="0.000000"/>
	<ActiveMove id="5" type="2" pos="-150,0,0" skillId="0" distance="0.000000" randomRange="0.000000"/>
	<ActiveMove id="6" type="2" pos="0,-150,0" skillId="0" distance="0.000000" randomRange="0.000000"/>
	<ActiveMove id="7" type="2" pos="0,150,0" skillId="0" distance="0.000000" randomRange="0.000000"/>
	<ActiveMove id="8" type="3" distance="300.000000" randomRange="10.000000" skillId="1150"/>
	<ActiveMove id="11" type="1" pos="-100,0,0" skillId="0"/>
	<ActiveMove id="18" type="3" distance="300.000000" randomRange="10.000000" skillId="2150"/>
	<ActiveMove id="21" type="1" pos="50,0,0" skillId="0"/>
	<ActiveMove id="22" type="1" pos="0,100,0" skillId="0"/>
	<ActiveMove id="23" type="1" pos="0,-100,0" skillId="0"/>
	<ActiveMove id="24" type="2" pos="0,250,0" skillId="1150" distance="0.000000" randomRange="50.000000"/>
	<ActiveMove id="31" type="1" pos="-200,0,0" skillId="0" distance="0.000000" randomRange="0.000000"/>
	<ActiveMove id="34" type="2" pos="0,250,0" skillId="2150" distance="0.000000" randomRange="50.000000"/>
	<ActiveMove id="6616" type="1" pos="-150,0,0" skillId="0" distance="0.000000" randomRange="0.000000"/>
	<ActiveMove id="6617" type="3" pos="" skillId="0" distance="200.000000" randomRange="10.000000"/>
	<ActiveMove id="6618" type="1" pos="-150,0,0" skillId="0" distance="0.000000" randomRange="0.000000"/>
	<ActiveMove id="6619" type="3" pos="" skillId="0" distance="200.000000" randomRange="10.000000"/>
	<ActiveMove id="6620" type="1" pos="-150.0000,0.0000,0.0000" skillId="0" distance="0.000000" randomRange="0.000000"/>
	<ActiveMove id="6621" type="3" pos="0.0000,-1.0000,0.0000" skillId="0" distance="200.000000" randomRange="10.000000"/>
	<ActiveMove id="6622" type="1" pos="-150.0000,0.0000,0.0000" skillId="0" distance="0.000000" randomRange="0.000000"/>
	<ActiveMove id="6623" type="3" pos="0.0000,-1.0000,0.0000" skillId="0" distance="200.000000" randomRange="10.000000"/>
	<ActiveMove id="6624" type="1" pos="-150.0000,0.0000,0.0000" skillId="0" distance="0.000000" randomRange="0.000000"/>
	<ActiveMove id="6625" type="3" pos="0.0000,-1.0000,0.0000" skillId="0" distance="200.000000" randomRange="10.000000"/>
	<ActiveMove id="6626" type="1" pos="-150.0000,0.0000,0.0000" skillId="0" distance="0.000000" randomRange="0.000000"/>
	<ActiveMove id="6627" type="3" pos="0.0000,-1.0000,0.0000" skillId="0" distance="200.000000" randomRange="10.000000"/>
	<ActiveMove id="6628" type="1" pos="-150.0000,0.0000,0.0000" skillId="0" distance="0.000000" randomRange="0.000000"/>
	<ActiveMove id="6629" type="3" pos="0.0000,-1.0000,0.0000" skillId="0" distance="200.000000" randomRange="10.000000"/>
	<ActiveMove id="6630" type="1" pos="-150.0000,0.0000,0.0000" skillId="0" distance="0.000000" randomRange="0.000000"/>
	<ActiveMove id="6631" type="3" pos="0.0000,-1.0000,0.0000" skillId="0" distance="200.000000" randomRange="10.000000"/>
	<ActiveMove id="6632" type="1" pos="-150.0000,0.0000,0.0000" skillId="0" distance="0.000000" randomRange="0.000000"/>
	<ActiveMove id="6633" type="3" pos="0.0000,-1.0000,0.0000" skillId="0" distance="200.000000" randomRange="10.000000"/>
	<ActiveMove id="6634" type="1" pos="-150.0000,0.0000,0.0000" skillId="0" distance="0.000000" randomRange="0.000000"/>
	<ActiveMove id="6635" type="3" pos="0.0000,-1.0000,0.0000" skillId="0" distance="200.000000" randomRange="10.000000"/>
	<ActiveMove id="6636" type="1" pos="-150.0000,0.0000,0.0000" skillId="0" distance="0.000000" randomRange="0.000000"/>
	<ActiveMove id="6637" type="3" pos="0.0000,-1.0000,0.0000" skillId="0" distance="200.000000" randomRange="10.000000"/>
	<ActiveMove id="6638" type="1" pos="-150.0000,0.0000,0.0000" skillId="0" distance="0.000000" randomRange="0.000000"/>
	<ActiveMove id="6639" type="3" pos="0.0000,-1.0000,0.0000" skillId="0" distance="200.000000" randomRange="10.000000"/>
	<ActiveMove id="6640" type="1" pos="-150.0000,0.0000,0.0000" skillId="0" distance="0.000000" randomRange="0.000000"/>
	<ActiveMove id="6641" type="3" pos="0.0000,-1.0000,0.0000" skillId="0" distance="200.000000" randomRange="10.000000"/>
	<ActiveMove id="6642" type="1" pos="-150.0000,0.0000,0.0000" skillId="0" distance="0.000000" randomRange="0.000000"/>
	<ActiveMove id="6643" type="3" pos="0.0000,-1.0000,0.0000" skillId="0" distance="200.000000" randomRange="10.000000"/>
	<ActiveMove id="6644" type="1" pos="-150.0000,0.0000,0.0000" skillId="0" distance="0.000000" randomRange="0.000000"/>
	<ActiveMove id="6645" type="3" pos="0.0000,-1.0000,0.0000" skillId="0" distance="200.000000" randomRange="10.000000"/>
	<ActiveMove id="6646" type="1" pos="-150.0000,0.0000,0.0000" skillId="0" distance="0.000000" randomRange="0.000000"/>
	<ActiveMove id="6647" type="3" pos="0.0000,-1.0000,0.0000" skillId="0" distance="200.000000" randomRange="10.000000"/>
	<ActiveMove id="6648" type="1" pos="-150,0,0" skillId="0" distance="0.000000" randomRange="0.000000"/>
	<ActiveMove id="6649" type="3" pos="" skillId="0" distance="200.000000" randomRange="10.000000"/>
	<ActiveMove id="6650" type="1" pos="-150,0,0" skillId="0" distance="0.000000" randomRange="0.000000"/>
	<ActiveMove id="6651" type="3" pos="" skillId="0" distance="200.000000" randomRange="10.000000"/>
	<ActiveMove id="6652" type="3" pos="0.0000,0.0000,0.0000" skillId="0" distance="50.000000" randomRange="30.000000"/>
	<ActiveMove id="6653" type="1" pos="100.6172,-107.6699,0.0000" skillId="0" distance="0.000000" randomRange="50.000000"/>
	<ActiveMove id="6654" type="1" pos="54.3984,52.2891,0.0000" skillId="0" distance="0.000000" randomRange="50.000000"/>
	<ActiveMove id="6655" type="3" pos="0.0000,0.0000,0.0000" skillId="0" distance="75.000000" randomRange="50.000000"/>
	<ActiveMove id="6656" type="3" pos="0.0000,0.0000,0.0000" skillId="0" distance="150.000000" randomRange="20.000000"/>
	<ActiveMove id="6657" type="1" pos="100.6172,-107.6699,0.0000" skillId="0" distance="0.000000" randomRange="50.000000"/>
	<ActiveMove id="6658" type="1" pos="54.3984,52.2891,0.0000" skillId="0" distance="0.000000" randomRange="50.000000"/>
	<ActiveMove id="6659" type="3" pos="0.0000,0.0000,0.0000" skillId="0" distance="75.000000" randomRange="50.000000"/>
	<ActiveMove id="6660" type="1" pos="60.1563,76.3701,0.0000" skillId="0" distance="0.000000" randomRange="50.000000"/>
	<ActiveMove id="6661" type="1" pos="-150,0,0" skillId="0" distance="0.000000" randomRange="0.000000"/>
	<ActiveMove id="6662" type="3" distance="200.000000" randomRange="10.000000" skillId="0"/>
	<ActiveMove id="55" type="5" distance="100.000000" randomRange="200.000000" skillId="1150"/>
	<ActiveMove id="56" type="5" distance="100.000000" randomRange="200.000000" skillId="2150"/>
	<ActiveMove id="57" type="5" distance="600.000000" randomRange="0.000000" skillId="1150"/>
	<ActiveMove id="58" type="5" distance="600.000000" randomRange="0.000000" skillId="2150"/>
	<ActiveMove id="59" type="1" pos="150,0,0" skillId="1150" distance="0.000000" randomRange="0.000000"/>
	<ActiveMove id="60" type="1" pos="150,0,0" skillId="2150" distance="0.000000" randomRange="0.000000"/>
	<ActiveMove id="70" type="5" distance="200.000000" randomRange="0.000000" skillId="1150"/>
	<ActiveMove id="71" type="5" distance="200.000000" randomRange="0.000000" skillId="2150"/>
	<ActiveMove id="6663" type="1" pos="450,0,0" skillId="1150" distance="0.000000" randomRange="0.000000"/>
	<ActiveMove id="6664" type="1" pos="450,0,0" skillId="2150" distance="0.000000" randomRange="0.000000"/>
	<ActiveMove id="6665" type="5" distance="600.000000" randomRange="0.000000" skillId="1150"/>
	<ActiveMove id="6666" type="5" distance="600.000000" randomRange="0.000000" skillId="2150"/>
	<ActiveMove id="6667" type="1" pos="450,0,0" skillId="1150" distance="0.000000" randomRange="0.000000"/>
	<ActiveMove id="6668" type="1" pos="450,0,0" skillId="2150" distance="0.000000" randomRange="0.000000"/>
	<ActiveMove id="6669" type="5" distance="600.000000" randomRange="0.000000" skillId="1150"/>
	<ActiveMove id="6670" type="5" distance="600.000000" randomRange="0.000000" skillId="2150"/>
	<ActiveMove id="6671" type="1" pos="450,0,0" skillId="1150" distance="0.000000" randomRange="0.000000"/>
	<ActiveMove id="6672" type="1" pos="450,0,0" skillId="2150" distance="0.000000" randomRange="0.000000"/>
	<ActiveMove id="6673" type="5" distance="600.000000" randomRange="0.000000" skillId="1150"/>
	<ActiveMove id="6674" type="5" distance="600.000000" randomRange="0.000000" skillId="2150"/>
	<ActiveMove id="6675" type="1" pos="450,0,0" skillId="1150" distance="0.000000" randomRange="0.000000"/>
	<ActiveMove id="6676" type="1" pos="450,0,0" skillId="2150" distance="0.000000" randomRange="0.000000"/>
	<ActiveMove id="6677" type="5" distance="100.000000" randomRange="200.000000" skillId="1150"/>
	<ActiveMove id="6678" type="5" distance="100.000000" randomRange="200.000000" skillId="2150"/>
	<ActiveMove id="6679" type="1" pos="450,0,0" skillId="1150" distance="0.000000" randomRange="0.000000"/>
	<ActiveMove id="6680" type="1" pos="450,0,0" skillId="2150" distance="0.000000" randomRange="0.000000"/>
	<ActiveMove id="6681" type="5" distance="100.000000" randomRange="200.000000" skillId="1150"/>
	<ActiveMove id="6682" type="5" distance="100.000000" randomRange="200.000000" skillId="2150"/>
	<ActiveMove id="6683" type="1" pos="450,0,0" skillId="1150" distance="0.000000" randomRange="0.000000"/>
	<ActiveMove id="6684" type="1" pos="450,0,0" skillId="2150" distance="0.000000" randomRange="0.000000"/>
	<ActiveMove id="6685" type="5" distance="100.000000" randomRange="200.000000" skillId="1150"/>
	<ActiveMove id="6686" type="5" distance="100.000000" randomRange="200.000000" skillId="2150"/>
	<ActiveMove id="6687" type="1" pos="450,0,0" skillId="1150" distance="0.000000" randomRange="0.000000"/>
	<ActiveMove id="6688" type="1" pos="450,0,0" skillId="2150" distance="0.000000" randomRange="0.000000"/>
	<ActiveMove id="6689" type="5" distance="100.000000" randomRange="200.000000" skillId="1150"/>
	<ActiveMove id="6690" type="5" distance="100.000000" randomRange="200.000000" skillId="2150"/>
	<ActiveMove id="888" type="1" pos="-365.3047,-1.5762,0.0000" skillId="0" distance="0.000000" randomRange="0.000000"/>
	<ActiveMove id="6691" type="1" pos="450,0,0" skillId="1150" distance="0.000000" randomRange="0.000000"/>
	<ActiveMove id="6692" type="1" pos="450,0,0" skillId="2150" distance="0.000000" randomRange="0.000000"/>
	<ActiveMove id="6693" type="5" distance="600.000000" randomRange="0.000000" skillId="1150"/>
	<ActiveMove id="6694" type="5" distance="600.000000" randomRange="0.000000" skillId="2150"/>
	<ActiveMove id="6695" type="1" pos="450,0,0" skillId="1150" distance="0.000000" randomRange="0.000000"/>
	<ActiveMove id="6696" type="1" pos="450,0,0" skillId="2150" distance="0.000000" randomRange="0.000000"/>
	<ActiveMove id="6697" type="1" pos="450,0,0" skillId="1150" distance="0.000000" randomRange="0.000000"/>
	<ActiveMove id="6698" type="1" pos="450,0,0" skillId="2150" distance="0.000000" randomRange="0.000000"/>
	<ActiveMove id="6699" type="5" distance="600.000000" randomRange="0.000000" skillId="1150"/>
	<ActiveMove id="6700" type="5" distance="600.000000" randomRange="0.000000" skillId="2150"/>
	<ActiveMove id="6701" type="1" pos="450,0,0" skillId="1150" distance="0.000000" randomRange="0.000000"/>
	<ActiveMove id="6702" type="1" pos="450,0,0" skillId="2150" distance="0.000000" randomRange="0.000000"/>
	<ActiveMove id="6703" type="1" pos="450,0,0" skillId="1150" distance="0.000000" randomRange="0.000000"/>
	<ActiveMove id="6704" type="1" pos="450,0,0" skillId="2150" distance="0.000000" randomRange="0.000000"/>
	<ActiveMove id="6705" type="5" distance="600.000000" randomRange="0.000000" skillId="1150"/>
	<ActiveMove id="6706" type="5" distance="600.000000" randomRange="0.000000" skillId="2150"/>
	<ActiveMove id="6707" type="1" pos="450,0,0" skillId="1150" distance="0.000000" randomRange="0.000000"/>
	<ActiveMove id="6708" type="1" pos="450,0,0" skillId="2150" distance="0.000000" randomRange="0.000000"/>
	<ActiveMove id="6709" type="1" pos="450,0,0" skillId="1150" distance="0.000000" randomRange="0.000000"/>
	<ActiveMove id="6710" type="1" pos="450,0,0" skillId="2150" distance="0.000000" randomRange="0.000000"/>
	<ActiveMove id="6711" type="1" pos="450,0,0" skillId="1150" distance="0.000000" randomRange="0.000000"/>
	<ActiveMove id="6712" type="1" pos="450,0,0" skillId="2150" distance="0.000000" randomRange="0.000000"/>
	<ActiveMove id="6713" type="5" distance="100.000000" randomRange="200.000000" skillId="1150"/>
	<ActiveMove id="6714" type="5" distance="100.000000" randomRange="200.000000" skillId="2150"/>
	<ActiveMove id="6715" type="1" pos="450,0,0" skillId="1150" distance="0.000000" randomRange="0.000000"/>
	<ActiveMove id="6716" type="1" pos="450,0,0" skillId="2150" distance="0.000000" randomRange="0.000000"/>
	<ActiveMove id="6717" type="1" pos="450,0,0" skillId="1150" distance="0.000000" randomRange="0.000000"/>
	<ActiveMove id="6718" type="1" pos="450,0,0" skillId="2150" distance="0.000000" randomRange="0.000000"/>
	<ActiveMove id="6719" type="1" pos="450,0,0" skillId="1150" distance="0.000000" randomRange="0.000000"/>
	<ActiveMove id="6720" type="1" pos="450,0,0" skillId="2150" distance="0.000000" randomRange="0.000000"/>
	<ActiveMove id="6721" type="1" pos="450,0,0" skillId="1150" distance="0.000000" randomRange="0.000000"/>
	<ActiveMove id="6722" type="1" pos="450,0,0" skillId="2150" distance="0.000000" randomRange="0.000000"/>
	<ActiveMove id="6723" type="5" distance="100.000000" randomRange="200.000000" skillId="1150"/>
	<ActiveMove id="6724" type="5" distance="100.000000" randomRange="200.000000" skillId="2150"/>
	<ActiveMove id="6725" type="1" pos="450,0,0" skillId="1150" distance="0.000000" randomRange="0.000000"/>
	<ActiveMove id="6726" type="1" pos="450,0,0" skillId="2150" distance="0.000000" randomRange="0.000000"/>
	<ActiveMove id="6727" type="1" pos="450,0,0" skillId="1150" distance="0.000000" randomRange="0.000000"/>
	<ActiveMove id="6728" type="1" pos="450,0,0" skillId="2150" distance="0.000000" randomRange="0.000000"/>
	<ActiveMove id="6729" type="1" pos="450,0,0" skillId="1150" distance="0.000000" randomRange="0.000000"/>
	<ActiveMove id="6730" type="1" pos="450,0,0" skillId="2150" distance="0.000000" randomRange="0.000000"/>
	<ActiveMove id="6731" type="1" pos="450,0,0" skillId="1150" distance="0.000000" randomRange="0.000000"/>
	<ActiveMove id="6732" type="1" pos="450,0,0" skillId="2150" distance="0.000000" randomRange="0.000000"/>
	<ActiveMove id="6733" type="5" distance="100.000000" randomRange="200.000000" skillId="1150"/>
	<ActiveMove id="6734" type="5" distance="100.000000" randomRange="200.000000" skillId="2150"/>
	<ActiveMove id="6735" type="1" pos="450,0,0" skillId="1150" distance="0.000000" randomRange="0.000000"/>
	<ActiveMove id="6736" type="1" pos="450,0,0" skillId="2150" distance="0.000000" randomRange="0.000000"/>
	<ActiveMove id="6737" type="1" pos="450,0,0" skillId="1150" distance="0.000000" randomRange="0.000000"/>
	<ActiveMove id="6738" type="1" pos="450,0,0" skillId="2150" distance="0.000000" randomRange="0.000000"/>
	<ActiveMove id="6739" type="1" pos="450,0,0" skillId="1150" distance="0.000000" randomRange="0.000000"/>
	<ActiveMove id="6740" type="1" pos="450,0,0" skillId="2150" distance="0.000000" randomRange="0.000000"/>
	<ActiveMove id="6741" type="1" pos="450,0,0" skillId="1150" distance="0.000000" randomRange="0.000000"/>
	<ActiveMove id="6742" type="1" pos="450,0,0" skillId="2150" distance="0.000000" randomRange="0.000000"/>
	<ActiveMove id="6743" type="5" distance="100.000000" randomRange="200.000000" skillId="1150"/>
	<ActiveMove id="6744" type="5" distance="100.000000" randomRange="200.000000" skillId="2150"/>
	<ActiveMove id="6745" type="1" pos="450,0,0" skillId="1150" distance="0.000000" randomRange="0.000000"/>
	<ActiveMove id="6746" type="1" pos="450,0,0" skillId="2150" distance="0.000000" randomRange="0.000000"/>
	<ActiveMove id="6747" type="1" pos="450,0,0" skillId="1150" distance="0.000000" randomRange="0.000000"/>
	<ActiveMove id="6748" type="1" pos="450,0,0" skillId="2150" distance="0.000000" randomRange="0.000000"/>
	<ActiveMove id="6749" type="1" pos="450,0,0" skillId="1150" distance="0.000000" randomRange="0.000000"/>
	<ActiveMove id="6750" type="1" pos="450,0,0" skillId="2150" distance="0.000000" randomRange="0.000000"/>
	<ActiveMove id="6751" type="5" distance="600.000000" randomRange="0.000000" skillId="1150"/>
	<ActiveMove id="6752" type="5" distance="600.000000" randomRange="0.000000" skillId="2150"/>
	<ActiveMove id="6753" type="1" pos="450,0,0" skillId="1150" distance="0.000000" randomRange="0.000000"/>
	<ActiveMove id="6754" type="1" pos="450,0,0" skillId="2150" distance="0.000000" randomRange="0.000000"/>
	<ActiveMove id="6755" type="1" pos="450,0,0" skillId="1150" distance="0.000000" randomRange="0.000000"/>
	<ActiveMove id="6756" type="1" pos="450,0,0" skillId="2150" distance="0.000000" randomRange="0.000000"/>
	<ActiveMove id="6757" type="5" distance="200.000000" randomRange="0.000000" skillId="1150"/>
	<ActiveMove id="6758" type="5" distance="200.000000" randomRange="0.000000" skillId="2150"/>
	<ActiveMove id="6759" type="1" pos="450,0,0" skillId="1150" distance="0.000000" randomRange="0.000000"/>
	<ActiveMove id="6760" type="1" pos="450,0,0" skillId="2150" distance="0.000000" randomRange="0.000000"/>
	<ActiveMove id="6761" type="5" distance="200.000000" randomRange="0.000000" skillId="1150"/>
	<ActiveMove id="6762" type="5" distance="200.000000" randomRange="0.000000" skillId="2150"/>
	<ActiveMove id="6763" type="1" pos="450,0,0" skillId="1150" distance="0.000000" randomRange="0.000000"/>
	<ActiveMove id="6764" type="1" pos="450,0,0" skillId="2150" distance="0.000000" randomRange="0.000000"/>
	<ActiveMove id="6765" type="5" distance="200.000000" randomRange="0.000000" skillId="1150"/>
	<ActiveMove id="6766" type="5" distance="200.000000" randomRange="0.000000" skillId="2150"/>
	<ActiveMove id="6767" type="1" pos="450,0,0" skillId="1150" distance="0.000000" randomRange="0.000000"/>
	<ActiveMove id="6768" type="1" pos="450,0,0" skillId="2150" distance="0.000000" randomRange="0.000000"/>
	<ActiveMove id="6769" type="5" distance="200.000000" randomRange="0.000000" skillId="1150"/>
	<ActiveMove id="6770" type="5" distance="200.000000" randomRange="0.000000" skillId="2150"/>
	<ActiveMove id="6771" type="1" pos="450,0,0" skillId="1150" distance="0.000000" randomRange="0.000000"/>
	<ActiveMove id="6772" type="1" pos="450,0,0" skillId="2150" distance="0.000000" randomRange="0.000000"/>
	<ActiveMove id="6773" type="5" distance="200.000000" randomRange="0.000000" skillId="1150"/>
	<ActiveMove id="6774" type="5" distance="200.000000" randomRange="0.000000" skillId="2150"/>
	<ActiveMove id="6775" type="1" pos="450,0,0" skillId="1150" distance="0.000000" randomRange="0.000000"/>
	<ActiveMove id="6776" type="1" pos="450,0,0" skillId="2150" distance="0.000000" randomRange="0.000000"/>
	<ActiveMove id="6777" type="5" distance="200.000000" randomRange="0.000000" skillId="1150"/>
	<ActiveMove id="6778" type="5" distance="200.000000" randomRange="0.000000" skillId="2150"/>
	<ActiveMove id="6779" type="1" pos="450,0,0" skillId="1150" distance="0.000000" randomRange="0.000000"/>
	<ActiveMove id="6780" type="1" pos="450,0,0" skillId="2150" distance="0.000000" randomRange="0.000000"/>
	<ActiveMove id="6781" type="1" pos="450,0,0" skillId="1150" distance="0.000000" randomRange="0.000000"/>
	<ActiveMove id="6782" type="1" pos="450,0,0" skillId="2150" distance="0.000000" randomRange="0.000000"/>
	<ActiveMove id="6783" type="5" distance="100.000000" randomRange="200.000000" skillId="1150"/>
	<ActiveMove id="6784" type="5" distance="100.000000" randomRange="200.000000" skillId="2150"/>
	<ActiveMove id="6785" type="1" pos="450,0,0" skillId="1150" distance="0.000000" randomRange="0.000000"/>
	<ActiveMove id="6786" type="1" pos="450,0,0" skillId="2150" distance="0.000000" randomRange="0.000000"/>
	<ActiveMove id="6787" type="1" pos="450,0,0" skillId="1150" distance="0.000000" randomRange="0.000000"/>
	<ActiveMove id="6788" type="1" pos="450,0,0" skillId="2150" distance="0.000000" randomRange="0.000000"/>
	<ActiveMove id="6789" type="5" distance="100.000000" randomRange="200.000000" skillId="1150"/>
	<ActiveMove id="6790" type="5" distance="100.000000" randomRange="200.000000" skillId="2150"/>
	<ActiveMove id="6791" type="1" pos="450,0,0" skillId="1150" distance="0.000000" randomRange="0.000000"/>
	<ActiveMove id="6792" type="1" pos="450,0,0" skillId="2150" distance="0.000000" randomRange="0.000000"/>
	<ActiveMove id="6793" type="1" pos="450,0,0" skillId="1150" distance="0.000000" randomRange="0.000000"/>
	<ActiveMove id="6794" type="1" pos="450,0,0" skillId="2150" distance="0.000000" randomRange="0.000000"/>
	<ActiveMove id="6795" type="5" distance="100.000000" randomRange="200.000000" skillId="1150"/>
	<ActiveMove id="6796" type="5" distance="100.000000" randomRange="200.000000" skillId="2150"/>
	<ActiveMove id="6797" type="1" pos="450,0,0" skillId="1150" distance="0.000000" randomRange="0.000000"/>
	<ActiveMove id="6798" type="1" pos="450,0,0" skillId="2150" distance="0.000000" randomRange="0.000000"/>
	<ActiveMove id="6799" type="1" pos="450,0,0" skillId="1150" distance="0.000000" randomRange="0.000000"/>
	<ActiveMove id="6800" type="1" pos="450,0,0" skillId="2150" distance="0.000000" randomRange="0.000000"/>
	<ActiveMove id="6801" type="5" distance="100.000000" randomRange="200.000000" skillId="1150"/>
	<ActiveMove id="6802" type="5" distance="100.000000" randomRange="200.000000" skillId="2150"/>
	<ActiveMove id="6803" type="1" pos="450,0,0" skillId="1150" distance="0.000000" randomRange="0.000000"/>
	<ActiveMove id="6804" type="1" pos="450,0,0" skillId="2150" distance="0.000000" randomRange="0.000000"/>
	<ActiveMove id="6805" type="1" pos="450,0,0" skillId="1150" distance="0.000000" randomRange="0.000000"/>
	<ActiveMove id="6806" type="1" pos="450,0,0" skillId="2150" distance="0.000000" randomRange="0.000000"/>
	<ActiveMove id="6807" type="5" distance="100.000000" randomRange="200.000000" skillId="1150"/>
	<ActiveMove id="6808" type="5" distance="100.000000" randomRange="200.000000" skillId="2150"/>
	<ActiveMove id="6809" type="1" pos="450,0,0" skillId="1150" distance="0.000000" randomRange="0.000000"/>
	<ActiveMove id="6810" type="1" pos="450,0,0" skillId="2150" distance="0.000000" randomRange="0.000000"/>
	<ActiveMove id="6811" type="1" pos="450,0,0" skillId="1150" distance="0.000000" randomRange="0.000000"/>
	<ActiveMove id="6812" type="1" pos="450,0,0" skillId="2150" distance="0.000000" randomRange="0.000000"/>
	<ActiveMove id="6813" type="5" distance="100.000000" randomRange="200.000000" skillId="1150"/>
	<ActiveMove id="6814" type="5" distance="100.000000" randomRange="200.000000" skillId="2150"/>
	<ActiveMove id="6815" type="1" pos="450,0,0" skillId="1150" distance="0.000000" randomRange="0.000000"/>
	<ActiveMove id="6816" type="1" pos="450,0,0" skillId="2150" distance="0.000000" randomRange="0.000000"/>
	<ActiveMove id="6817" type="1" pos="450,0,0" skillId="1150" distance="0.000000" randomRange="0.000000"/>
	<ActiveMove id="6818" type="1" pos="450,0,0" skillId="2150" distance="0.000000" randomRange="0.000000"/>
	<ActiveMove id="6819" type="5" distance="100.000000" randomRange="200.000000" skillId="1150"/>
	<ActiveMove id="6820" type="5" distance="100.000000" randomRange="200.000000" skillId="2150"/>
	<ActiveMove id="6821" type="1" pos="450,0,0" skillId="1150" distance="0.000000" randomRange="0.000000"/>
	<ActiveMove id="6822" type="1" pos="450,0,0" skillId="2150" distance="0.000000" randomRange="0.000000"/>
	<ActiveMove id="6823" type="1" pos="450,0,0" skillId="1150" distance="0.000000" randomRange="0.000000"/>
	<ActiveMove id="6824" type="1" pos="450,0,0" skillId="2150" distance="0.000000" randomRange="0.000000"/>
	<ActiveMove id="6825" type="5" distance="100.000000" randomRange="200.000000" skillId="1150"/>
	<ActiveMove id="6826" type="5" distance="100.000000" randomRange="200.000000" skillId="2150"/>
	<ActiveMove id="6827" type="1" pos="450,0,0" skillId="1150" distance="0.000000" randomRange="0.000000"/>
	<ActiveMove id="6828" type="1" pos="450,0,0" skillId="2150" distance="0.000000" randomRange="0.000000"/>
	<ActiveMove id="6829" type="5" distance="200.000000" randomRange="0.000000" skillId="1150"/>
	<ActiveMove id="6830" type="5" distance="200.000000" randomRange="0.000000" skillId="2150"/>
	<ActiveMove id="6831" type="1" pos="450,0,0" skillId="1150" distance="0.000000" randomRange="0.000000"/>
	<ActiveMove id="6832" type="1" pos="450,0,0" skillId="2150" distance="0.000000" randomRange="0.000000"/>
	<ActiveMove id="6833" type="5" distance="200.000000" randomRange="0.000000" skillId="1150"/>
	<ActiveMove id="6834" type="5" distance="200.000000" randomRange="0.000000" skillId="2150"/>
	<ActiveMove id="6835" type="1" pos="450,0,0" skillId="1150" distance="0.000000" randomRange="0.000000"/>
	<ActiveMove id="6836" type="1" pos="450,0,0" skillId="2150" distance="0.000000" randomRange="0.000000"/>
	<ActiveMove id="6837" type="5" distance="200.000000" randomRange="0.000000" skillId="1150"/>
	<ActiveMove id="6838" type="5" distance="200.000000" randomRange="0.000000" skillId="2150"/>
	<ActiveMove id="6839" type="1" pos="450,0,0" skillId="1150" distance="0.000000" randomRange="0.000000"/>
	<ActiveMove id="6840" type="1" pos="450,0,0" skillId="2150" distance="0.000000" randomRange="0.000000"/>
	<ActiveMove id="6841" type="5" distance="200.000000" randomRange="0.000000" skillId="1150"/>
	<ActiveMove id="6842" type="5" distance="200.000000" randomRange="0.000000" skillId="2150"/>
	<ActiveMove id="6843" type="1" pos="450,0,0" skillId="1150" distance="0.000000" randomRange="0.000000"/>
	<ActiveMove id="6844" type="1" pos="450,0,0" skillId="2150" distance="0.000000" randomRange="0.000000"/>
	<ActiveMove id="6845" type="5" distance="200.000000" randomRange="0.000000" skillId="1150"/>
	<ActiveMove id="6846" type="5" distance="200.000000" randomRange="0.000000" skillId="2150"/>
	<ActiveMove id="6847" type="1" pos="450,0,0" skillId="1150" distance="0.000000" randomRange="0.000000"/>
	<ActiveMove id="6848" type="1" pos="450,0,0" skillId="2150" distance="0.000000" randomRange="0.000000"/>
	<ActiveMove id="6849" type="5" distance="200.000000" randomRange="0.000000" skillId="1150"/>
	<ActiveMove id="6850" type="5" distance="200.000000" randomRange="0.000000" skillId="2150"/>
	<ActiveMove id="6851" type="1" pos="450,0,0" skillId="1150" distance="0.000000" randomRange="0.000000"/>
	<ActiveMove id="6852" type="1" pos="450,0,0" skillId="2150" distance="0.000000" randomRange="0.000000"/>
	<ActiveMove id="6853" type="5" distance="200.000000" randomRange="0.000000" skillId="1150"/>
	<ActiveMove id="6854" type="5" distance="200.000000" randomRange="0.000000" skillId="2150"/>
	<ActiveMove id="6855" type="1" pos="450,0,0" skillId="1150" distance="0.000000" randomRange="0.000000"/>
	<ActiveMove id="6856" type="1" pos="450,0,0" skillId="2150" distance="0.000000" randomRange="0.000000"/>
	<ActiveMove id="6857" type="5" distance="200.000000" randomRange="0.000000" skillId="1150"/>
	<ActiveMove id="6858" type="5" distance="200.000000" randomRange="0.000000" skillId="2150"/>
	<ActiveMove id="6859" type="1" pos="450,0,0" skillId="1150" distance="0.000000" randomRange="0.000000"/>
	<ActiveMove id="6860" type="1" pos="450,0,0" skillId="2150" distance="0.000000" randomRange="0.000000"/>
	<ActiveMove id="6861" type="1" pos="450,0,0" skillId="1150" distance="0.000000" randomRange="0.000000"/>
	<ActiveMove id="6862" type="1" pos="450,0,0" skillId="2150" distance="0.000000" randomRange="0.000000"/>
	<ActiveMove id="6863" type="5" distance="100.000000" randomRange="200.000000" skillId="1150"/>
	<ActiveMove id="6864" type="5" distance="100.000000" randomRange="200.000000" skillId="2150"/>
	<ActiveMove id="6865" type="1" pos="450,0,0" skillId="1150" distance="0.000000" randomRange="0.000000"/>
	<ActiveMove id="6866" type="1" pos="450,0,0" skillId="2150" distance="0.000000" randomRange="0.000000"/>
	<ActiveMove id="6867" type="1" pos="450,0,0" skillId="1150" distance="0.000000" randomRange="0.000000"/>
	<ActiveMove id="6868" type="1" pos="450,0,0" skillId="2150" distance="0.000000" randomRange="0.000000"/>
	<ActiveMove id="6869" type="5" distance="100.000000" randomRange="200.000000" skillId="1150"/>
	<ActiveMove id="6870" type="5" distance="100.000000" randomRange="200.000000" skillId="2150"/>
	<ActiveMove id="6871" type="1" pos="450,0,0" skillId="1150" distance="0.000000" randomRange="0.000000"/>
	<ActiveMove id="6872" type="1" pos="450,0,0" skillId="2150" distance="0.000000" randomRange="0.000000"/>
	<ActiveMove id="6873" type="1" pos="450,0,0" skillId="1150" distance="0.000000" randomRange="0.000000"/>
	<ActiveMove id="6874" type="1" pos="450,0,0" skillId="2150" distance="0.000000" randomRange="0.000000"/>
	<ActiveMove id="6875" type="5" distance="100.000000" randomRange="200.000000" skillId="1150"/>
	<ActiveMove id="6876" type="5" distance="100.000000" randomRange="200.000000" skillId="2150"/>
	<ActiveMove id="6877" type="1" pos="450,0,0" skillId="1150" distance="0.000000" randomRange="0.000000"/>
	<ActiveMove id="6878" type="1" pos="450,0,0" skillId="2150" distance="0.000000" randomRange="0.000000"/>
	<ActiveMove id="6879" type="1" pos="450,0,0" skillId="1150" distance="0.000000" randomRange="0.000000"/>
	<ActiveMove id="6880" type="1" pos="450,0,0" skillId="2150" distance="0.000000" randomRange="0.000000"/>
	<ActiveMove id="6881" type="5" distance="100.000000" randomRange="200.000000" skillId="1150"/>
	<ActiveMove id="6882" type="5" distance="100.000000" randomRange="200.000000" skillId="2150"/>
	<ActiveMove id="6883" type="1" pos="450,0,0" skillId="1150" distance="0.000000" randomRange="0.000000"/>
	<ActiveMove id="6884" type="1" pos="450,0,0" skillId="2150" distance="0.000000" randomRange="0.000000"/>
	<ActiveMove id="6885" type="1" pos="450,0,0" skillId="1150" distance="0.000000" randomRange="0.000000"/>
	<ActiveMove id="6886" type="1" pos="450,0,0" skillId="2150" distance="0.000000" randomRange="0.000000"/>
	<ActiveMove id="6887" type="5" distance="100.000000" randomRange="200.000000" skillId="1150"/>
	<ActiveMove id="6888" type="5" distance="100.000000" randomRange="200.000000" skillId="2150"/>
	<ActiveMove id="6889" type="1" pos="450,0,0" skillId="1150" distance="0.000000" randomRange="0.000000"/>
	<ActiveMove id="6890" type="1" pos="450,0,0" skillId="2150" distance="0.000000" randomRange="0.000000"/>
	<ActiveMove id="6891" type="1" pos="450,0,0" skillId="1150" distance="0.000000" randomRange="0.000000"/>
	<ActiveMove id="6892" type="1" pos="450,0,0" skillId="2150" distance="0.000000" randomRange="0.000000"/>
	<ActiveMove id="6893" type="5" distance="100.000000" randomRange="200.000000" skillId="1150"/>
	<ActiveMove id="6894" type="5" distance="100.000000" randomRange="200.000000" skillId="2150"/>
	<ActiveMove id="6895" type="1" pos="450,0,0" skillId="1150" distance="0.000000" randomRange="0.000000"/>
	<ActiveMove id="6896" type="1" pos="450,0,0" skillId="2150" distance="0.000000" randomRange="0.000000"/>
	<ActiveMove id="6897" type="1" pos="450,0,0" skillId="1150" distance="0.000000" randomRange="0.000000"/>
	<ActiveMove id="6898" type="1" pos="450,0,0" skillId="2150" distance="0.000000" randomRange="0.000000"/>
	<ActiveMove id="6899" type="5" distance="100.000000" randomRange="200.000000" skillId="1150"/>
	<ActiveMove id="6900" type="5" distance="100.000000" randomRange="200.000000" skillId="2150"/>
	<ActiveMove id="6901" type="1" pos="450,0,0" skillId="1150" distance="0.000000" randomRange="0.000000"/>
	<ActiveMove id="6902" type="1" pos="450,0,0" skillId="2150" distance="0.000000" randomRange="0.000000"/>
	<ActiveMove id="6903" type="1" pos="450,0,0" skillId="1150" distance="0.000000" randomRange="0.000000"/>
	<ActiveMove id="6904" type="1" pos="450,0,0" skillId="2150" distance="0.000000" randomRange="0.000000"/>
	<ActiveMove id="6905" type="5" distance="100.000000" randomRange="200.000000" skillId="1150"/>
	<ActiveMove id="6906" type="5" distance="100.000000" randomRange="200.000000" skillId="2150"/>
	<ActiveMove id="6907" type="1" pos="450,0,0" skillId="1150" distance="0.000000" randomRange="0.000000"/>
	<ActiveMove id="6908" type="1" pos="450,0,0" skillId="2150" distance="0.000000" randomRange="0.000000"/>
	<ActiveMove id="6909" type="5" distance="200.000000" randomRange="0.000000" skillId="1150"/>
	<ActiveMove id="6910" type="5" distance="200.000000" randomRange="0.000000" skillId="2150"/>
	<ActiveMove id="6911" type="1" pos="450,0,0" skillId="1150" distance="0.000000" randomRange="0.000000"/>
	<ActiveMove id="6912" type="1" pos="450,0,0" skillId="2150" distance="0.000000" randomRange="0.000000"/>
	<ActiveMove id="6913" type="5" distance="200.000000" randomRange="0.000000" skillId="1150"/>
	<ActiveMove id="6914" type="5" distance="200.000000" randomRange="0.000000" skillId="2150"/>
	<ActiveMove id="6915" type="1" pos="450,0,0" skillId="1150" distance="0.000000" randomRange="0.000000"/>
	<ActiveMove id="6916" type="1" pos="450,0,0" skillId="2150" distance="0.000000" randomRange="0.000000"/>
	<ActiveMove id="6917" type="5" distance="200.000000" randomRange="0.000000" skillId="1150"/>
	<ActiveMove id="6918" type="5" distance="200.000000" randomRange="0.000000" skillId="2150"/>
	<ActiveMove id="6919" type="1" pos="450,0,0" skillId="1150" distance="0.000000" randomRange="0.000000"/>
	<ActiveMove id="6920" type="1" pos="450,0,0" skillId="2150" distance="0.000000" randomRange="0.000000"/>
	<ActiveMove id="6921" type="5" distance="200.000000" randomRange="0.000000" skillId="1150"/>
	<ActiveMove id="6922" type="5" distance="200.000000" randomRange="0.000000" skillId="2150"/>
	<ActiveMove id="6923" type="1" pos="450,0,0" skillId="1150" distance="0.000000" randomRange="0.000000"/>
	<ActiveMove id="6924" type="1" pos="450,0,0" skillId="2150" distance="0.000000" randomRange="0.000000"/>
	<ActiveMove id="6925" type="5" distance="200.000000" randomRange="0.000000" skillId="1150"/>
	<ActiveMove id="6926" type="5" distance="200.000000" randomRange="0.000000" skillId="2150"/>
	<ActiveMove id="6927" type="1" pos="450,0,0" skillId="1150" distance="0.000000" randomRange="0.000000"/>
	<ActiveMove id="6928" type="1" pos="450,0,0" skillId="2150" distance="0.000000" randomRange="0.000000"/>
	<ActiveMove id="6929" type="5" distance="200.000000" randomRange="0.000000" skillId="1150"/>
	<ActiveMove id="6930" type="5" distance="200.000000" randomRange="0.000000" skillId="2150"/>
	<ActiveMove id="6931" type="1" pos="450,0,0" skillId="1150" distance="0.000000" randomRange="0.000000"/>
	<ActiveMove id="6932" type="1" pos="450,0,0" skillId="2150" distance="0.000000" randomRange="0.000000"/>
	<ActiveMove id="6933" type="5" distance="200.000000" randomRange="0.000000" skillId="1150"/>
	<ActiveMove id="6934" type="5" distance="200.000000" randomRange="0.000000" skillId="2150"/>
	<ActiveMove id="6935" type="1" pos="450,0,0" skillId="1150" distance="0.000000" randomRange="0.000000"/>
	<ActiveMove id="6936" type="1" pos="450,0,0" skillId="2150" distance="0.000000" randomRange="0.000000"/>
	<ActiveMove id="6937" type="5" distance="200.000000" randomRange="0.000000" skillId="1150"/>
	<ActiveMove id="6938" type="5" distance="200.000000" randomRange="0.000000" skillId="2150"/>
	<ActiveMove id="6939" type="1" pos="450,0,0" skillId="1150" distance="0.000000" randomRange="0.000000"/>
	<ActiveMove id="6940" type="1" pos="450,0,0" skillId="2150" distance="0.000000" randomRange="0.000000"/>
	<ActiveMove id="6941" type="1" pos="450,0,0" skillId="1150" distance="0.000000" randomRange="0.000000"/>
	<ActiveMove id="6942" type="1" pos="450,0,0" skillId="2150" distance="0.000000" randomRange="0.000000"/>
	<ActiveMove id="6943" type="5" distance="100.000000" randomRange="200.000000" skillId="1150"/>
	<ActiveMove id="6944" type="5" distance="100.000000" randomRange="200.000000" skillId="2150"/>
	<ActiveMove id="6945" type="1" pos="450,0,0" skillId="1150" distance="0.000000" randomRange="0.000000"/>
	<ActiveMove id="6946" type="1" pos="450,0,0" skillId="2150" distance="0.000000" randomRange="0.000000"/>
	<ActiveMove id="6947" type="1" pos="450,0,0" skillId="1150" distance="0.000000" randomRange="0.000000"/>
	<ActiveMove id="6948" type="1" pos="450,0,0" skillId="2150" distance="0.000000" randomRange="0.000000"/>
	<ActiveMove id="6949" type="5" distance="100.000000" randomRange="200.000000" skillId="1150"/>
	<ActiveMove id="6950" type="5" distance="100.000000" randomRange="200.000000" skillId="2150"/>
	<ActiveMove id="6951" type="1" pos="450,0,0" skillId="1150" distance="0.000000" randomRange="0.000000"/>
	<ActiveMove id="6952" type="1" pos="450,0,0" skillId="2150" distance="0.000000" randomRange="0.000000"/>
	<ActiveMove id="6953" type="1" pos="450,0,0" skillId="1150" distance="0.000000" randomRange="0.000000"/>
	<ActiveMove id="6954" type="1" pos="450,0,0" skillId="2150" distance="0.000000" randomRange="0.000000"/>
	<ActiveMove id="6955" type="5" distance="100.000000" randomRange="200.000000" skillId="1150"/>
	<ActiveMove id="6956" type="5" distance="100.000000" randomRange="200.000000" skillId="2150"/>
	<ActiveMove id="6957" type="1" pos="450,0,0" skillId="1150" distance="0.000000" randomRange="0.000000"/>
	<ActiveMove id="6958" type="1" pos="450,0,0" skillId="2150" distance="0.000000" randomRange="0.000000"/>
	<ActiveMove id="6959" type="1" pos="450,0,0" skillId="1150" distance="0.000000" randomRange="0.000000"/>
	<ActiveMove id="6960" type="1" pos="450,0,0" skillId="2150" distance="0.000000" randomRange="0.000000"/>
	<ActiveMove id="6961" type="5" distance="100.000000" randomRange="200.000000" skillId="1150"/>
	<ActiveMove id="6962" type="5" distance="100.000000" randomRange="200.000000" skillId="2150"/>
	<ActiveMove id="6963" type="1" pos="450,0,0" skillId="1150" distance="0.000000" randomRange="0.000000"/>
	<ActiveMove id="6964" type="1" pos="450,0,0" skillId="2150" distance="0.000000" randomRange="0.000000"/>
	<ActiveMove id="6965" type="1" pos="450,0,0" skillId="1150" distance="0.000000" randomRange="0.000000"/>
	<ActiveMove id="6966" type="1" pos="450,0,0" skillId="2150" distance="0.000000" randomRange="0.000000"/>
	<ActiveMove id="6967" type="5" distance="100.000000" randomRange="200.000000" skillId="1150"/>
	<ActiveMove id="6968" type="5" distance="100.000000" randomRange="200.000000" skillId="2150"/>
	<ActiveMove id="6969" type="1" pos="450,0,0" skillId="1150" distance="0.000000" randomRange="0.000000"/>
	<ActiveMove id="6970" type="1" pos="450,0,0" skillId="2150" distance="0.000000" randomRange="0.000000"/>
	<ActiveMove id="6971" type="1" pos="450,0,0" skillId="1150" distance="0.000000" randomRange="0.000000"/>
	<ActiveMove id="6972" type="1" pos="450,0,0" skillId="2150" distance="0.000000" randomRange="0.000000"/>
	<ActiveMove id="6973" type="5" distance="100.000000" randomRange="200.000000" skillId="1150"/>
	<ActiveMove id="6974" type="5" distance="100.000000" randomRange="200.000000" skillId="2150"/>
	<ActiveMove id="6975" type="1" pos="450,0,0" skillId="1150" distance="0.000000" randomRange="0.000000"/>
	<ActiveMove id="6976" type="1" pos="450,0,0" skillId="2150" distance="0.000000" randomRange="0.000000"/>
	<ActiveMove id="6977" type="1" pos="450,0,0" skillId="1150" distance="0.000000" randomRange="0.000000"/>
	<ActiveMove id="6978" type="1" pos="450,0,0" skillId="2150" distance="0.000000" randomRange="0.000000"/>
	<ActiveMove id="6979" type="5" distance="100.000000" randomRange="200.000000" skillId="1150"/>
	<ActiveMove id="6980" type="5" distance="100.000000" randomRange="200.000000" skillId="2150"/>
	<ActiveMove id="6981" type="1" pos="450,0,0" skillId="1150" distance="0.000000" randomRange="0.000000"/>
	<ActiveMove id="6982" type="1" pos="450,0,0" skillId="2150" distance="0.000000" randomRange="0.000000"/>
	<ActiveMove id="6983" type="1" pos="450,0,0" skillId="1150" distance="0.000000" randomRange="0.000000"/>
	<ActiveMove id="6984" type="1" pos="450,0,0" skillId="2150" distance="0.000000" randomRange="0.000000"/>
	<ActiveMove id="6985" type="5" distance="100.000000" randomRange="200.000000" skillId="1150"/>
	<ActiveMove id="6986" type="5" distance="100.000000" randomRange="200.000000" skillId="2150"/>
	<ActiveMove id="6987" type="1" pos="450,0,0" skillId="1150" distance="0.000000" randomRange="0.000000"/>
	<ActiveMove id="6988" type="1" pos="450,0,0" skillId="2150" distance="0.000000" randomRange="0.000000"/>
	<ActiveMove id="6989" type="5" distance="200.000000" randomRange="0.000000" skillId="1150"/>
	<ActiveMove id="6990" type="5" distance="200.000000" randomRange="0.000000" skillId="2150"/>
	<ActiveMove id="6991" type="1" pos="450,0,0" skillId="1150" distance="0.000000" randomRange="0.000000"/>
	<ActiveMove id="6992" type="1" pos="450,0,0" skillId="2150" distance="0.000000" randomRange="0.000000"/>
	<ActiveMove id="6993" type="5" distance="200.000000" randomRange="0.000000" skillId="1150"/>
	<ActiveMove id="6994" type="5" distance="200.000000" randomRange="0.000000" skillId="2150"/>
	<ActiveMove id="6995" type="1" pos="450,0,0" skillId="1150" distance="0.000000" randomRange="0.000000"/>
	<ActiveMove id="6996" type="1" pos="450,0,0" skillId="2150" distance="0.000000" randomRange="0.000000"/>
	<ActiveMove id="6997" type="5" distance="200.000000" randomRange="0.000000" skillId="1150"/>
	<ActiveMove id="6998" type="5" distance="200.000000" randomRange="0.000000" skillId="2150"/>
	<ActiveMove id="6999" type="1" pos="450,0,0" skillId="1150" distance="0.000000" randomRange="0.000000"/>
	<ActiveMove id="7000" type="1" pos="450,0,0" skillId="2150" distance="0.000000" randomRange="0.000000"/>
	<ActiveMove id="7001" type="5" distance="200.000000" randomRange="0.000000" skillId="1150"/>
	<ActiveMove id="7002" type="5" distance="200.000000" randomRange="0.000000" skillId="2150"/>
	<ActiveMove id="7003" type="1" pos="450,0,0" skillId="1150" distance="0.000000" randomRange="0.000000"/>
	<ActiveMove id="7004" type="1" pos="450,0,0" skillId="2150" distance="0.000000" randomRange="0.000000"/>
	<ActiveMove id="7005" type="5" distance="200.000000" randomRange="0.000000" skillId="1150"/>
	<ActiveMove id="7006" type="5" distance="200.000000" randomRange="0.000000" skillId="2150"/>
	<ActiveMove id="7007" type="1" pos="450,0,0" skillId="1150" distance="0.000000" randomRange="0.000000"/>
	<ActiveMove id="7008" type="1" pos="450,0,0" skillId="2150" distance="0.000000" randomRange="0.000000"/>
	<ActiveMove id="7009" type="5" distance="200.000000" randomRange="0.000000" skillId="1150"/>
	<ActiveMove id="7010" type="5" distance="200.000000" randomRange="0.000000" skillId="2150"/>
	<ActiveMove id="7011" type="1" pos="450,0,0" skillId="1150" distance="0.000000" randomRange="0.000000"/>
	<ActiveMove id="7012" type="1" pos="450,0,0" skillId="2150" distance="0.000000" randomRange="0.000000"/>
	<ActiveMove id="7013" type="5" distance="200.000000" randomRange="0.000000" skillId="1150"/>
	<ActiveMove id="7014" type="5" distance="200.000000" randomRange="0.000000" skillId="2150"/>
	<ActiveMove id="7015" type="1" pos="450,0,0" skillId="1150" distance="0.000000" randomRange="0.000000"/>
	<ActiveMove id="7016" type="1" pos="450,0,0" skillId="2150" distance="0.000000" randomRange="0.000000"/>
	<ActiveMove id="7017" type="5" distance="200.000000" randomRange="0.000000" skillId="1150"/>
	<ActiveMove id="7018" type="5" distance="200.000000" randomRange="0.000000" skillId="2150"/>
	<ActiveMove id="7019" type="1" pos="450,0,0" skillId="1150" distance="0.000000" randomRange="0.000000"/>
	<ActiveMove id="7020" type="1" pos="450,0,0" skillId="2150" distance="0.000000" randomRange="0.000000"/>
	<ActiveMove id="7021" type="1" pos="450,0,0" skillId="1150" distance="0.000000" randomRange="0.000000"/>
	<ActiveMove id="7022" type="1" pos="450,0,0" skillId="2150" distance="0.000000" randomRange="0.000000"/>
	<ActiveMove id="7023" type="5" distance="100.000000" randomRange="200.000000" skillId="1150"/>
	<ActiveMove id="7024" type="5" distance="100.000000" randomRange="200.000000" skillId="2150"/>
	<ActiveMove id="7025" type="1" pos="450,0,0" skillId="1150" distance="0.000000" randomRange="0.000000"/>
	<ActiveMove id="7026" type="1" pos="450,0,0" skillId="2150" distance="0.000000" randomRange="0.000000"/>
	<ActiveMove id="7027" type="1" pos="450,0,0" skillId="1150" distance="0.000000" randomRange="0.000000"/>
	<ActiveMove id="7028" type="1" pos="450,0,0" skillId="2150" distance="0.000000" randomRange="0.000000"/>
	<ActiveMove id="7029" type="5" distance="100.000000" randomRange="200.000000" skillId="1150"/>
	<ActiveMove id="7030" type="5" distance="100.000000" randomRange="200.000000" skillId="2150"/>
	<ActiveMove id="7031" type="1" pos="450,0,0" skillId="1150" distance="0.000000" randomRange="0.000000"/>
	<ActiveMove id="7032" type="1" pos="450,0,0" skillId="2150" distance="0.000000" randomRange="0.000000"/>
	<ActiveMove id="7033" type="1" pos="450,0,0" skillId="1150" distance="0.000000" randomRange="0.000000"/>
	<ActiveMove id="7034" type="1" pos="450,0,0" skillId="2150" distance="0.000000" randomRange="0.000000"/>
	<ActiveMove id="7035" type="5" distance="100.000000" randomRange="200.000000" skillId="1150"/>
	<ActiveMove id="7036" type="5" distance="100.000000" randomRange="200.000000" skillId="2150"/>
	<ActiveMove id="7037" type="1" pos="450,0,0" skillId="1150" distance="0.000000" randomRange="0.000000"/>
	<ActiveMove id="7038" type="1" pos="450,0,0" skillId="2150" distance="0.000000" randomRange="0.000000"/>
	<ActiveMove id="7039" type="1" pos="450,0,0" skillId="1150" distance="0.000000" randomRange="0.000000"/>
	<ActiveMove id="7040" type="1" pos="450,0,0" skillId="2150" distance="0.000000" randomRange="0.000000"/>
	<ActiveMove id="7041" type="5" distance="100.000000" randomRange="200.000000" skillId="1150"/>
	<ActiveMove id="7042" type="5" distance="100.000000" randomRange="200.000000" skillId="2150"/>
	<ActiveMove id="7043" type="1" pos="450,0,0" skillId="1150" distance="0.000000" randomRange="0.000000"/>
	<ActiveMove id="7044" type="1" pos="450,0,0" skillId="2150" distance="0.000000" randomRange="0.000000"/>
	<ActiveMove id="7045" type="1" pos="450,0,0" skillId="1150" distance="0.000000" randomRange="0.000000"/>
	<ActiveMove id="7046" type="1" pos="450,0,0" skillId="2150" distance="0.000000" randomRange="0.000000"/>
	<ActiveMove id="7047" type="5" distance="100.000000" randomRange="200.000000" skillId="1150"/>
	<ActiveMove id="7048" type="5" distance="100.000000" randomRange="200.000000" skillId="2150"/>
	<ActiveMove id="7049" type="1" pos="450,0,0" skillId="1150" distance="0.000000" randomRange="0.000000"/>
	<ActiveMove id="7050" type="1" pos="450,0,0" skillId="2150" distance="0.000000" randomRange="0.000000"/>
	<ActiveMove id="7051" type="1" pos="450,0,0" skillId="1150" distance="0.000000" randomRange="0.000000"/>
	<ActiveMove id="7052" type="1" pos="450,0,0" skillId="2150" distance="0.000000" randomRange="0.000000"/>
	<ActiveMove id="7053" type="5" distance="100.000000" randomRange="200.000000" skillId="1150"/>
	<ActiveMove id="7054" type="5" distance="100.000000" randomRange="200.000000" skillId="2150"/>
	<ActiveMove id="7055" type="1" pos="450,0,0" skillId="1150" distance="0.000000" randomRange="0.000000"/>
	<ActiveMove id="7056" type="1" pos="450,0,0" skillId="2150" distance="0.000000" randomRange="0.000000"/>
	<ActiveMove id="7057" type="1" pos="450,0,0" skillId="1150" distance="0.000000" randomRange="0.000000"/>
	<ActiveMove id="7058" type="1" pos="450,0,0" skillId="2150" distance="0.000000" randomRange="0.000000"/>
	<ActiveMove id="7059" type="5" distance="100.000000" randomRange="200.000000" skillId="1150"/>
	<ActiveMove id="7060" type="5" distance="100.000000" randomRange="200.000000" skillId="2150"/>
	<ActiveMove id="7061" type="1" pos="450,0,0" skillId="1150" distance="0.000000" randomRange="0.000000"/>
	<ActiveMove id="7062" type="1" pos="450,0,0" skillId="2150" distance="0.000000" randomRange="0.000000"/>
	<ActiveMove id="7063" type="1" pos="450,0,0" skillId="1150" distance="0.000000" randomRange="0.000000"/>
	<ActiveMove id="7064" type="1" pos="450,0,0" skillId="2150" distance="0.000000" randomRange="0.000000"/>
	<ActiveMove id="7065" type="5" distance="100.000000" randomRange="200.000000" skillId="1150"/>
	<ActiveMove id="7066" type="5" distance="100.000000" randomRange="200.000000" skillId="2150"/>
	<ActiveMove id="7067" type="1" pos="450,0,0" skillId="1150" distance="0.000000" randomRange="0.000000"/>
	<ActiveMove id="7068" type="1" pos="450,0,0" skillId="2150" distance="0.000000" randomRange="0.000000"/>
	<ActiveMove id="7069" type="5" distance="200.000000" randomRange="0.000000" skillId="1150"/>
	<ActiveMove id="7070" type="5" distance="200.000000" randomRange="0.000000" skillId="2150"/>
	<ActiveMove id="7071" type="1" pos="450,0,0" skillId="1150" distance="0.000000" randomRange="0.000000"/>
	<ActiveMove id="7072" type="1" pos="450,0,0" skillId="2150" distance="0.000000" randomRange="0.000000"/>
	<ActiveMove id="7073" type="5" distance="200.000000" randomRange="0.000000" skillId="1150"/>
	<ActiveMove id="7074" type="5" distance="200.000000" randomRange="0.000000" skillId="2150"/>
	<ActiveMove id="7075" type="1" pos="450,0,0" skillId="1150" distance="0.000000" randomRange="0.000000"/>
	<ActiveMove id="7076" type="1" pos="450,0,0" skillId="2150" distance="0.000000" randomRange="0.000000"/>
	<ActiveMove id="7077" type="5" distance="200.000000" randomRange="0.000000" skillId="1150"/>
	<ActiveMove id="7078" type="5" distance="200.000000" randomRange="0.000000" skillId="2150"/>
	<ActiveMove id="7079" type="1" pos="450,0,0" skillId="1150" distance="0.000000" randomRange="0.000000"/>
	<ActiveMove id="7080" type="1" pos="450,0,0" skillId="2150" distance="0.000000" randomRange="0.000000"/>
	<ActiveMove id="7081" type="5" distance="200.000000" randomRange="0.000000" skillId="1150"/>
	<ActiveMove id="7082" type="5" distance="200.000000" randomRange="0.000000" skillId="2150"/>
	<ActiveMove id="7083" type="1" pos="450,0,0" skillId="1150" distance="0.000000" randomRange="0.000000"/>
	<ActiveMove id="7084" type="1" pos="450,0,0" skillId="2150" distance="0.000000" randomRange="0.000000"/>
	<ActiveMove id="7085" type="5" distance="200.000000" randomRange="0.000000" skillId="1150"/>
	<ActiveMove id="7086" type="5" distance="200.000000" randomRange="0.000000" skillId="2150"/>
	<ActiveMove id="7087" type="1" pos="450,0,0" skillId="1150" distance="0.000000" randomRange="0.000000"/>
	<ActiveMove id="7088" type="1" pos="450,0,0" skillId="2150" distance="0.000000" randomRange="0.000000"/>
	<ActiveMove id="7089" type="5" distance="200.000000" randomRange="0.000000" skillId="1150"/>
	<ActiveMove id="7090" type="5" distance="200.000000" randomRange="0.000000" skillId="2150"/>
	<ActiveMove id="7091" type="1" pos="450,0,0" skillId="1150" distance="0.000000" randomRange="0.000000"/>
	<ActiveMove id="7092" type="1" pos="450,0,0" skillId="2150" distance="0.000000" randomRange="0.000000"/>
	<ActiveMove id="7093" type="5" distance="200.000000" randomRange="0.000000" skillId="1150"/>
	<ActiveMove id="7094" type="5" distance="200.000000" randomRange="0.000000" skillId="2150"/>
	<ActiveMove id="7095" type="1" pos="450,0,0" skillId="1150" distance="0.000000" randomRange="0.000000"/>
	<ActiveMove id="7096" type="1" pos="450,0,0" skillId="2150" distance="0.000000" randomRange="0.000000"/>
	<ActiveMove id="7097" type="5" distance="200.000000" randomRange="0.000000" skillId="1150"/>
	<ActiveMove id="7098" type="5" distance="200.000000" randomRange="0.000000" skillId="2150"/>
	<ActiveMove id="7099" type="1" pos="450,0,0" skillId="1150" distance="0.000000" randomRange="0.000000"/>
	<ActiveMove id="7100" type="1" pos="450,0,0" skillId="2150" distance="0.000000" randomRange="0.000000"/>
	<ActiveMove id="7101" type="1" pos="450,0,0" skillId="1150" distance="0.000000" randomRange="0.000000"/>
	<ActiveMove id="7102" type="1" pos="450,0,0" skillId="2150" distance="0.000000" randomRange="0.000000"/>
	<ActiveMove id="7103" type="5" distance="100.000000" randomRange="200.000000" skillId="1150"/>
	<ActiveMove id="7104" type="5" distance="100.000000" randomRange="200.000000" skillId="2150"/>
	<ActiveMove id="7105" type="1" pos="450,0,0" skillId="1150" distance="0.000000" randomRange="0.000000"/>
	<ActiveMove id="7106" type="1" pos="450,0,0" skillId="2150" distance="0.000000" randomRange="0.000000"/>
	<ActiveMove id="7107" type="1" pos="450,0,0" skillId="1150" distance="0.000000" randomRange="0.000000"/>
	<ActiveMove id="7108" type="1" pos="450,0,0" skillId="2150" distance="0.000000" randomRange="0.000000"/>
	<ActiveMove id="7109" type="5" distance="100.000000" randomRange="200.000000" skillId="1150"/>
	<ActiveMove id="7110" type="5" distance="100.000000" randomRange="200.000000" skillId="2150"/>
	<ActiveMove id="7111" type="1" pos="450,0,0" skillId="1150" distance="0.000000" randomRange="0.000000"/>
	<ActiveMove id="7112" type="1" pos="450,0,0" skillId="2150" distance="0.000000" randomRange="0.000000"/>
	<ActiveMove id="7113" type="1" pos="450,0,0" skillId="1150" distance="0.000000" randomRange="0.000000"/>
	<ActiveMove id="7114" type="1" pos="450,0,0" skillId="2150" distance="0.000000" randomRange="0.000000"/>
	<ActiveMove id="7115" type="5" distance="100.000000" randomRange="200.000000" skillId="1150"/>
	<ActiveMove id="7116" type="5" distance="100.000000" randomRange="200.000000" skillId="2150"/>
	<ActiveMove id="7117" type="1" pos="450,0,0" skillId="1150" distance="0.000000" randomRange="0.000000"/>
	<ActiveMove id="7118" type="1" pos="450,0,0" skillId="2150" distance="0.000000" randomRange="0.000000"/>
	<ActiveMove id="7119" type="1" pos="450,0,0" skillId="1150" distance="0.000000" randomRange="0.000000"/>
	<ActiveMove id="7120" type="1" pos="450,0,0" skillId="2150" distance="0.000000" randomRange="0.000000"/>
	<ActiveMove id="7121" type="5" distance="100.000000" randomRange="200.000000" skillId="1150"/>
	<ActiveMove id="7122" type="5" distance="100.000000" randomRange="200.000000" skillId="2150"/>
	<ActiveMove id="7123" type="1" pos="450,0,0" skillId="1150" distance="0.000000" randomRange="0.000000"/>
	<ActiveMove id="7124" type="1" pos="450,0,0" skillId="2150" distance="0.000000" randomRange="0.000000"/>
	<ActiveMove id="7125" type="1" pos="450,0,0" skillId="1150" distance="0.000000" randomRange="0.000000"/>
	<ActiveMove id="7126" type="1" pos="450,0,0" skillId="2150" distance="0.000000" randomRange="0.000000"/>
	<ActiveMove id="7127" type="5" distance="100.000000" randomRange="200.000000" skillId="1150"/>
	<ActiveMove id="7128" type="5" distance="100.000000" randomRange="200.000000" skillId="2150"/>
	<ActiveMove id="7129" type="1" pos="450,0,0" skillId="1150" distance="0.000000" randomRange="0.000000"/>
	<ActiveMove id="7130" type="1" pos="450,0,0" skillId="2150" distance="0.000000" randomRange="0.000000"/>
	<ActiveMove id="7131" type="1" pos="450,0,0" skillId="1150" distance="0.000000" randomRange="0.000000"/>
	<ActiveMove id="7132" type="1" pos="450,0,0" skillId="2150" distance="0.000000" randomRange="0.000000"/>
	<ActiveMove id="7133" type="5" distance="100.000000" randomRange="200.000000" skillId="1150"/>
	<ActiveMove id="7134" type="5" distance="100.000000" randomRange="200.000000" skillId="2150"/>
	<ActiveMove id="7135" type="1" pos="450,0,0" skillId="1150" distance="0.000000" randomRange="0.000000"/>
	<ActiveMove id="7136" type="1" pos="450,0,0" skillId="2150" distance="0.000000" randomRange="0.000000"/>
	<ActiveMove id="7137" type="1" pos="450,0,0" skillId="1150" distance="0.000000" randomRange="0.000000"/>
	<ActiveMove id="7138" type="1" pos="450,0,0" skillId="2150" distance="0.000000" randomRange="0.000000"/>
	<ActiveMove id="7139" type="5" distance="100.000000" randomRange="200.000000" skillId="1150"/>
	<ActiveMove id="7140" type="5" distance="100.000000" randomRange="200.000000" skillId="2150"/>
	<ActiveMove id="7141" type="1" pos="450,0,0" skillId="1150" distance="0.000000" randomRange="0.000000"/>
	<ActiveMove id="7142" type="1" pos="450,0,0" skillId="2150" distance="0.000000" randomRange="0.000000"/>
	<ActiveMove id="7143" type="1" pos="450,0,0" skillId="1150" distance="0.000000" randomRange="0.000000"/>
	<ActiveMove id="7144" type="1" pos="450,0,0" skillId="2150" distance="0.000000" randomRange="0.000000"/>
	<ActiveMove id="7145" type="5" distance="100.000000" randomRange="200.000000" skillId="1150"/>
	<ActiveMove id="7146" type="5" distance="100.000000" randomRange="200.000000" skillId="2150"/>
	<ActiveMove id="7147" type="1" pos="450,0,0" skillId="1150" distance="0.000000" randomRange="0.000000"/>
	<ActiveMove id="7148" type="1" pos="450,0,0" skillId="2150" distance="0.000000" randomRange="0.000000"/>
	<ActiveMove id="7149" type="5" distance="200.000000" randomRange="0.000000" skillId="1150"/>
	<ActiveMove id="7150" type="5" distance="200.000000" randomRange="0.000000" skillId="2150"/>
	<ActiveMove id="7151" type="1" pos="450,0,0" skillId="1150" distance="0.000000" randomRange="0.000000"/>
	<ActiveMove id="7152" type="1" pos="450,0,0" skillId="2150" distance="0.000000" randomRange="0.000000"/>
	<ActiveMove id="7153" type="5" distance="200.000000" randomRange="0.000000" skillId="1150"/>
	<ActiveMove id="7154" type="5" distance="200.000000" randomRange="0.000000" skillId="2150"/>
	<ActiveMove id="7155" type="1" pos="450,0,0" skillId="1150" distance="0.000000" randomRange="0.000000"/>
	<ActiveMove id="7156" type="1" pos="450,0,0" skillId="2150" distance="0.000000" randomRange="0.000000"/>
	<ActiveMove id="7157" type="5" distance="200.000000" randomRange="0.000000" skillId="1150"/>
	<ActiveMove id="7158" type="5" distance="200.000000" randomRange="0.000000" skillId="2150"/>
	<ActiveMove id="7159" type="1" pos="450,0,0" skillId="1150" distance="0.000000" randomRange="0.000000"/>
	<ActiveMove id="7160" type="1" pos="450,0,0" skillId="2150" distance="0.000000" randomRange="0.000000"/>
	<ActiveMove id="7161" type="5" distance="200.000000" randomRange="0.000000" skillId="1150"/>
	<ActiveMove id="7162" type="5" distance="200.000000" randomRange="0.000000" skillId="2150"/>
	<ActiveMove id="7163" type="1" pos="450,0,0" skillId="1150" distance="0.000000" randomRange="0.000000"/>
	<ActiveMove id="7164" type="1" pos="450,0,0" skillId="2150" distance="0.000000" randomRange="0.000000"/>
	<ActiveMove id="7165" type="5" distance="200.000000" randomRange="0.000000" skillId="1150"/>
	<ActiveMove id="7166" type="5" distance="200.000000" randomRange="0.000000" skillId="2150"/>
	<ActiveMove id="7167" type="1" pos="450,0,0" skillId="1150" distance="0.000000" randomRange="0.000000"/>
	<ActiveMove id="7168" type="1" pos="450,0,0" skillId="2150" distance="0.000000" randomRange="0.000000"/>
	<ActiveMove id="7169" type="5" distance="200.000000" randomRange="0.000000" skillId="1150"/>
	<ActiveMove id="7170" type="5" distance="200.000000" randomRange="0.000000" skillId="2150"/>
	<ActiveMove id="7171" type="1" pos="450,0,0" skillId="1150" distance="0.000000" randomRange="0.000000"/>
	<ActiveMove id="7172" type="1" pos="450,0,0" skillId="2150" distance="0.000000" randomRange="0.000000"/>
	<ActiveMove id="7173" type="5" distance="200.000000" randomRange="0.000000" skillId="1150"/>
	<ActiveMove id="7174" type="5" distance="200.000000" randomRange="0.000000" skillId="2150"/>
	<ActiveMove id="7175" type="1" pos="450,0,0" skillId="1150" distance="0.000000" randomRange="0.000000"/>
	<ActiveMove id="7176" type="1" pos="450,0,0" skillId="2150" distance="0.000000" randomRange="0.000000"/>
	<ActiveMove id="7177" type="5" distance="200.000000" randomRange="0.000000" skillId="1150"/>
	<ActiveMove id="7178" type="5" distance="200.000000" randomRange="0.000000" skillId="2150"/>
	<ActiveMove id="7179" type="1" pos="450,0,0" skillId="1150" distance="0.000000" randomRange="0.000000"/>
	<ActiveMove id="7180" type="1" pos="450,0,0" skillId="2150" distance="0.000000" randomRange="0.000000"/>
	<ActiveMove id="7181" type="1" pos="450,0,0" skillId="1150" distance="0.000000" randomRange="0.000000"/>
	<ActiveMove id="7182" type="1" pos="450,0,0" skillId="2150" distance="0.000000" randomRange="0.000000"/>
	<ActiveMove id="7183" type="5" distance="100.000000" randomRange="200.000000" skillId="1150"/>
	<ActiveMove id="7184" type="5" distance="100.000000" randomRange="200.000000" skillId="2150"/>
	<ActiveMove id="7185" type="1" pos="450,0,0" skillId="1150" distance="0.000000" randomRange="0.000000"/>
	<ActiveMove id="7186" type="1" pos="450,0,0" skillId="2150" distance="0.000000" randomRange="0.000000"/>
	<ActiveMove id="7187" type="1" pos="450,0,0" skillId="1150" distance="0.000000" randomRange="0.000000"/>
	<ActiveMove id="7188" type="1" pos="450,0,0" skillId="2150" distance="0.000000" randomRange="0.000000"/>
	<ActiveMove id="7189" type="5" distance="100.000000" randomRange="200.000000" skillId="1150"/>
	<ActiveMove id="7190" type="5" distance="100.000000" randomRange="200.000000" skillId="2150"/>
	<ActiveMove id="7191" type="1" pos="450,0,0" skillId="1150" distance="0.000000" randomRange="0.000000"/>
	<ActiveMove id="7192" type="1" pos="450,0,0" skillId="2150" distance="0.000000" randomRange="0.000000"/>
	<ActiveMove id="7193" type="1" pos="450,0,0" skillId="1150" distance="0.000000" randomRange="0.000000"/>
	<ActiveMove id="7194" type="1" pos="450,0,0" skillId="2150" distance="0.000000" randomRange="0.000000"/>
	<ActiveMove id="7195" type="5" distance="100.000000" randomRange="200.000000" skillId="1150"/>
	<ActiveMove id="7196" type="5" distance="100.000000" randomRange="200.000000" skillId="2150"/>
	<ActiveMove id="7197" type="1" pos="450,0,0" skillId="1150" distance="0.000000" randomRange="0.000000"/>
	<ActiveMove id="7198" type="1" pos="450,0,0" skillId="2150" distance="0.000000" randomRange="0.000000"/>
	<ActiveMove id="7199" type="1" pos="450,0,0" skillId="1150" distance="0.000000" randomRange="0.000000"/>
	<ActiveMove id="7200" type="1" pos="450,0,0" skillId="2150" distance="0.000000" randomRange="0.000000"/>
	<ActiveMove id="7201" type="5" distance="100.000000" randomRange="200.000000" skillId="1150"/>
	<ActiveMove id="7202" type="5" distance="100.000000" randomRange="200.000000" skillId="2150"/>
	<ActiveMove id="7203" type="1" pos="450,0,0" skillId="1150" distance="0.000000" randomRange="0.000000"/>
	<ActiveMove id="7204" type="1" pos="450,0,0" skillId="2150" distance="0.000000" randomRange="0.000000"/>
	<ActiveMove id="7205" type="1" pos="450,0,0" skillId="1150" distance="0.000000" randomRange="0.000000"/>
	<ActiveMove id="7206" type="1" pos="450,0,0" skillId="2150" distance="0.000000" randomRange="0.000000"/>
	<ActiveMove id="7207" type="5" distance="100.000000" randomRange="200.000000" skillId="1150"/>
	<ActiveMove id="7208" type="5" distance="100.000000" randomRange="200.000000" skillId="2150"/>
	<ActiveMove id="7209" type="1" pos="450,0,0" skillId="1150" distance="0.000000" randomRange="0.000000"/>
	<ActiveMove id="7210" type="1" pos="450,0,0" skillId="2150" distance="0.000000" randomRange="0.000000"/>
	<ActiveMove id="7211" type="1" pos="450,0,0" skillId="1150" distance="0.000000" randomRange="0.000000"/>
	<ActiveMove id="7212" type="1" pos="450,0,0" skillId="2150" distance="0.000000" randomRange="0.000000"/>
	<ActiveMove id="7213" type="5" distance="100.000000" randomRange="200.000000" skillId="1150"/>
	<ActiveMove id="7214" type="5" distance="100.000000" randomRange="200.000000" skillId="2150"/>
	<ActiveMove id="7215" type="1" pos="450,0,0" skillId="1150" distance="0.000000" randomRange="0.000000"/>
	<ActiveMove id="7216" type="1" pos="450,0,0" skillId="2150" distance="0.000000" randomRange="0.000000"/>
	<ActiveMove id="7217" type="1" pos="450,0,0" skillId="1150" distance="0.000000" randomRange="0.000000"/>
	<ActiveMove id="7218" type="1" pos="450,0,0" skillId="2150" distance="0.000000" randomRange="0.000000"/>
	<ActiveMove id="7219" type="5" distance="100.000000" randomRange="200.000000" skillId="1150"/>
	<ActiveMove id="7220" type="5" distance="100.000000" randomRange="200.000000" skillId="2150"/>
	<ActiveMove id="7221" type="1" pos="450,0,0" skillId="1150" distance="0.000000" randomRange="0.000000"/>
	<ActiveMove id="7222" type="1" pos="450,0,0" skillId="2150" distance="0.000000" randomRange="0.000000"/>
	<ActiveMove id="7223" type="1" pos="450,0,0" skillId="1150" distance="0.000000" randomRange="0.000000"/>
	<ActiveMove id="7224" type="1" pos="450,0,0" skillId="2150" distance="0.000000" randomRange="0.000000"/>
	<ActiveMove id="7225" type="5" distance="100.000000" randomRange="200.000000" skillId="1150"/>
	<ActiveMove id="7226" type="5" distance="100.000000" randomRange="200.000000" skillId="2150"/>
	<ActiveMove id="7227" type="1" pos="450,0,0" skillId="1150" distance="0.000000" randomRange="0.000000"/>
	<ActiveMove id="7228" type="1" pos="450,0,0" skillId="2150" distance="0.000000" randomRange="0.000000"/>
	<ActiveMove id="7229" type="5" distance="200.000000" randomRange="0.000000" skillId="1150"/>
	<ActiveMove id="7230" type="5" distance="200.000000" randomRange="0.000000" skillId="2150"/>
	<ActiveMove id="7231" type="1" pos="450,0,0" skillId="1150" distance="0.000000" randomRange="0.000000"/>
	<ActiveMove id="7232" type="1" pos="450,0,0" skillId="2150" distance="0.000000" randomRange="0.000000"/>
	<ActiveMove id="7233" type="5" distance="200.000000" randomRange="0.000000" skillId="1150"/>
	<ActiveMove id="7234" type="5" distance="200.000000" randomRange="0.000000" skillId="2150"/>
	<ActiveMove id="7235" type="1" pos="450,0,0" skillId="1150" distance="0.000000" randomRange="0.000000"/>
	<ActiveMove id="7236" type="1" pos="450,0,0" skillId="2150" distance="0.000000" randomRange="0.000000"/>
	<ActiveMove id="7237" type="5" distance="200.000000" randomRange="0.000000" skillId="1150"/>
	<ActiveMove id="7238" type="5" distance="200.000000" randomRange="0.000000" skillId="2150"/>
	<ActiveMove id="7239" type="1" pos="450,0,0" skillId="1150" distance="0.000000" randomRange="0.000000"/>
	<ActiveMove id="7240" type="1" pos="450,0,0" skillId="2150" distance="0.000000" randomRange="0.000000"/>
	<ActiveMove id="7241" type="5" distance="200.000000" randomRange="0.000000" skillId="1150"/>
	<ActiveMove id="7242" type="5" distance="200.000000" randomRange="0.000000" skillId="2150"/>
	<ActiveMove id="7243" type="1" pos="450,0,0" skillId="1150" distance="0.000000" randomRange="0.000000"/>
	<ActiveMove id="7244" type="1" pos="450,0,0" skillId="2150" distance="0.000000" randomRange="0.000000"/>
	<ActiveMove id="7245" type="5" distance="200.000000" randomRange="0.000000" skillId="1150"/>
	<ActiveMove id="7246" type="5" distance="200.000000" randomRange="0.000000" skillId="2150"/>
	<ActiveMove id="7247" type="1" pos="450,0,0" skillId="1150" distance="0.000000" randomRange="0.000000"/>
	<ActiveMove id="7248" type="1" pos="450,0,0" skillId="2150" distance="0.000000" randomRange="0.000000"/>
	<ActiveMove id="7249" type="5" distance="200.000000" randomRange="0.000000" skillId="1150"/>
	<ActiveMove id="7250" type="5" distance="200.000000" randomRange="0.000000" skillId="2150"/>
	<ActiveMove id="7251" type="1" pos="450,0,0" skillId="1150" distance="0.000000" randomRange="0.000000"/>
	<ActiveMove id="7252" type="1" pos="450,0,0" skillId="2150" distance="0.000000" randomRange="0.000000"/>
	<ActiveMove id="7253" type="5" distance="200.000000" randomRange="0.000000" skillId="1150"/>
	<ActiveMove id="7254" type="5" distance="200.000000" randomRange="0.000000" skillId="2150"/>
	<ActiveMove id="7255" type="1" pos="450,0,0" skillId="1150" distance="0.000000" randomRange="0.000000"/>
	<ActiveMove id="7256" type="1" pos="450,0,0" skillId="2150" distance="0.000000" randomRange="0.000000"/>
	<ActiveMove id="7257" type="5" distance="200.000000" randomRange="0.000000" skillId="1150"/>
	<ActiveMove id="7258" type="5" distance="200.000000" randomRange="0.000000" skillId="2150"/>
	<ActiveMove id="7259" type="1" pos="450,0,0" skillId="1150" distance="0.000000" randomRange="0.000000"/>
	<ActiveMove id="7260" type="1" pos="450,0,0" skillId="2150" distance="0.000000" randomRange="0.000000"/>
	<ActiveMove id="7261" type="1" pos="450,0,0" skillId="1150" distance="0.000000" randomRange="0.000000"/>
	<ActiveMove id="7262" type="1" pos="450,0,0" skillId="2150" distance="0.000000" randomRange="0.000000"/>
	<ActiveMove id="7263" type="5" distance="100.000000" randomRange="200.000000" skillId="1150"/>
	<ActiveMove id="7264" type="5" distance="100.000000" randomRange="200.000000" skillId="2150"/>
	<ActiveMove id="7265" type="1" pos="450,0,0" skillId="1150" distance="0.000000" randomRange="0.000000"/>
	<ActiveMove id="7266" type="1" pos="450,0,0" skillId="2150" distance="0.000000" randomRange="0.000000"/>
	<ActiveMove id="7267" type="1" pos="450,0,0" skillId="1150" distance="0.000000" randomRange="0.000000"/>
	<ActiveMove id="7268" type="1" pos="450,0,0" skillId="2150" distance="0.000000" randomRange="0.000000"/>
	<ActiveMove id="7269" type="5" distance="100.000000" randomRange="200.000000" skillId="1150"/>
	<ActiveMove id="7270" type="5" distance="100.000000" randomRange="200.000000" skillId="2150"/>
	<ActiveMove id="7271" type="1" pos="450,0,0" skillId="1150" distance="0.000000" randomRange="0.000000"/>
	<ActiveMove id="7272" type="1" pos="450,0,0" skillId="2150" distance="0.000000" randomRange="0.000000"/>
	<ActiveMove id="7273" type="1" pos="450,0,0" skillId="1150" distance="0.000000" randomRange="0.000000"/>
	<ActiveMove id="7274" type="1" pos="450,0,0" skillId="2150" distance="0.000000" randomRange="0.000000"/>
	<ActiveMove id="7275" type="5" distance="100.000000" randomRange="200.000000" skillId="1150"/>
	<ActiveMove id="7276" type="5" distance="100.000000" randomRange="200.000000" skillId="2150"/>
	<ActiveMove id="7277" type="1" pos="450,0,0" skillId="1150" distance="0.000000" randomRange="0.000000"/>
	<ActiveMove id="7278" type="1" pos="450,0,0" skillId="2150" distance="0.000000" randomRange="0.000000"/>
	<ActiveMove id="7279" type="1" pos="450,0,0" skillId="1150" distance="0.000000" randomRange="0.000000"/>
	<ActiveMove id="7280" type="1" pos="450,0,0" skillId="2150" distance="0.000000" randomRange="0.000000"/>
	<ActiveMove id="7281" type="5" distance="100.000000" randomRange="200.000000" skillId="1150"/>
	<ActiveMove id="7282" type="5" distance="100.000000" randomRange="200.000000" skillId="2150"/>
	<ActiveMove id="7283" type="1" pos="450,0,0" skillId="1150" distance="0.000000" randomRange="0.000000"/>
	<ActiveMove id="7284" type="1" pos="450,0,0" skillId="2150" distance="0.000000" randomRange="0.000000"/>
	<ActiveMove id="7285" type="1" pos="450,0,0" skillId="1150" distance="0.000000" randomRange="0.000000"/>
	<ActiveMove id="7286" type="1" pos="450,0,0" skillId="2150" distance="0.000000" randomRange="0.000000"/>
	<ActiveMove id="7287" type="5" distance="100.000000" randomRange="200.000000" skillId="1150"/>
	<ActiveMove id="7288" type="5" distance="100.000000" randomRange="200.000000" skillId="2150"/>
	<ActiveMove id="7289" type="1" pos="450,0,0" skillId="1150" distance="0.000000" randomRange="0.000000"/>
	<ActiveMove id="7290" type="1" pos="450,0,0" skillId="2150" distance="0.000000" randomRange="0.000000"/>
	<ActiveMove id="7291" type="1" pos="450,0,0" skillId="1150" distance="0.000000" randomRange="0.000000"/>
	<ActiveMove id="7292" type="1" pos="450,0,0" skillId="2150" distance="0.000000" randomRange="0.000000"/>
	<ActiveMove id="7293" type="5" distance="100.000000" randomRange="200.000000" skillId="1150"/>
	<ActiveMove id="7294" type="5" distance="100.000000" randomRange="200.000000" skillId="2150"/>
	<ActiveMove id="7295" type="1" pos="450,0,0" skillId="1150" distance="0.000000" randomRange="0.000000"/>
	<ActiveMove id="7296" type="1" pos="450,0,0" skillId="2150" distance="0.000000" randomRange="0.000000"/>
	<ActiveMove id="7297" type="1" pos="450,0,0" skillId="1150" distance="0.000000" randomRange="0.000000"/>
	<ActiveMove id="7298" type="1" pos="450,0,0" skillId="2150" distance="0.000000" randomRange="0.000000"/>
	<ActiveMove id="7299" type="5" distance="100.000000" randomRange="200.000000" skillId="1150"/>
	<ActiveMove id="7300" type="5" distance="100.000000" randomRange="200.000000" skillId="2150"/>
	<ActiveMove id="7301" type="1" pos="450,0,0" skillId="1150" distance="0.000000" randomRange="0.000000"/>
	<ActiveMove id="7302" type="1" pos="450,0,0" skillId="2150" distance="0.000000" randomRange="0.000000"/>
	<ActiveMove id="7303" type="1" pos="450,0,0" skillId="1150" distance="0.000000" randomRange="0.000000"/>
	<ActiveMove id="7304" type="1" pos="450,0,0" skillId="2150" distance="0.000000" randomRange="0.000000"/>
	<ActiveMove id="7305" type="5" distance="100.000000" randomRange="200.000000" skillId="1150"/>
	<ActiveMove id="7306" type="5" distance="100.000000" randomRange="200.000000" skillId="2150"/>
	<ActiveMove id="7307" type="1" pos="450,0,0" skillId="1150" distance="0.000000" randomRange="0.000000"/>
	<ActiveMove id="7308" type="1" pos="450,0,0" skillId="2150" distance="0.000000" randomRange="0.000000"/>
	<ActiveMove id="7309" type="5" distance="200.000000" randomRange="0.000000" skillId="1150"/>
	<ActiveMove id="7310" type="5" distance="200.000000" randomRange="0.000000" skillId="2150"/>
	<ActiveMove id="7311" type="1" pos="450,0,0" skillId="1150" distance="0.000000" randomRange="0.000000"/>
	<ActiveMove id="7312" type="1" pos="450,0,0" skillId="2150" distance="0.000000" randomRange="0.000000"/>
	<ActiveMove id="7313" type="5" distance="200.000000" randomRange="0.000000" skillId="1150"/>
	<ActiveMove id="7314" type="5" distance="200.000000" randomRange="0.000000" skillId="2150"/>
	<ActiveMove id="7315" type="1" pos="450,0,0" skillId="1150" distance="0.000000" randomRange="0.000000"/>
	<ActiveMove id="7316" type="1" pos="450,0,0" skillId="2150" distance="0.000000" randomRange="0.000000"/>
	<ActiveMove id="7317" type="5" distance="200.000000" randomRange="0.000000" skillId="1150"/>
	<ActiveMove id="7318" type="5" distance="200.000000" randomRange="0.000000" skillId="2150"/>
	<ActiveMove id="7319" type="1" pos="450,0,0" skillId="1150" distance="0.000000" randomRange="0.000000"/>
	<ActiveMove id="7320" type="1" pos="450,0,0" skillId="2150" distance="0.000000" randomRange="0.000000"/>
	<ActiveMove id="7321" type="5" distance="200.000000" randomRange="0.000000" skillId="1150"/>
	<ActiveMove id="7322" type="5" distance="200.000000" randomRange="0.000000" skillId="2150"/>
	<ActiveMove id="7323" type="1" pos="450,0,0" skillId="1150" distance="0.000000" randomRange="0.000000"/>
	<ActiveMove id="7324" type="1" pos="450,0,0" skillId="2150" distance="0.000000" randomRange="0.000000"/>
	<ActiveMove id="7325" type="5" distance="200.000000" randomRange="0.000000" skillId="1150"/>
	<ActiveMove id="7326" type="5" distance="200.000000" randomRange="0.000000" skillId="2150"/>
	<ActiveMove id="7327" type="1" pos="450,0,0" skillId="1150" distance="0.000000" randomRange="0.000000"/>
	<ActiveMove id="7328" type="1" pos="450,0,0" skillId="2150" distance="0.000000" randomRange="0.000000"/>
	<ActiveMove id="7329" type="5" distance="200.000000" randomRange="0.000000" skillId="1150"/>
	<ActiveMove id="7330" type="5" distance="200.000000" randomRange="0.000000" skillId="2150"/>
	<ActiveMove id="7331" type="1" pos="450,0,0" skillId="1150" distance="0.000000" randomRange="0.000000"/>
	<ActiveMove id="7332" type="1" pos="450,0,0" skillId="2150" distance="0.000000" randomRange="0.000000"/>
	<ActiveMove id="7333" type="5" distance="200.000000" randomRange="0.000000" skillId="1150"/>
	<ActiveMove id="7334" type="5" distance="200.000000" randomRange="0.000000" skillId="2150"/>
	<ActiveMove id="7335" type="1" pos="450,0,0" skillId="1150" distance="0.000000" randomRange="0.000000"/>
	<ActiveMove id="7336" type="1" pos="450,0,0" skillId="2150" distance="0.000000" randomRange="0.000000"/>
	<ActiveMove id="7337" type="5" distance="200.000000" randomRange="0.000000" skillId="1150"/>
	<ActiveMove id="7338" type="5" distance="200.000000" randomRange="0.000000" skillId="2150"/>
	<ActiveMove id="7339" type="1" pos="450,0,0" skillId="1150" distance="0.000000" randomRange="0.000000"/>
	<ActiveMove id="7340" type="1" pos="450,0,0" skillId="2150" distance="0.000000" randomRange="0.000000"/>
	<ActiveMove id="7341" type="1" pos="450,0,0" skillId="1150" distance="0.000000" randomRange="0.000000"/>
	<ActiveMove id="7342" type="1" pos="450,0,0" skillId="2150" distance="0.000000" randomRange="0.000000"/>
	<ActiveMove id="7343" type="5" distance="100.000000" randomRange="200.000000" skillId="1150"/>
	<ActiveMove id="7344" type="5" distance="100.000000" randomRange="200.000000" skillId="2150"/>
	<ActiveMove id="7345" type="1" pos="450,0,0" skillId="1150" distance="0.000000" randomRange="0.000000"/>
	<ActiveMove id="7346" type="1" pos="450,0,0" skillId="2150" distance="0.000000" randomRange="0.000000"/>
	<ActiveMove id="7347" type="1" pos="450,0,0" skillId="1150" distance="0.000000" randomRange="0.000000"/>
	<ActiveMove id="7348" type="1" pos="450,0,0" skillId="2150" distance="0.000000" randomRange="0.000000"/>
	<ActiveMove id="7349" type="5" distance="100.000000" randomRange="200.000000" skillId="1150"/>
	<ActiveMove id="7350" type="5" distance="100.000000" randomRange="200.000000" skillId="2150"/>
	<ActiveMove id="7351" type="1" pos="450,0,0" skillId="1150" distance="0.000000" randomRange="0.000000"/>
	<ActiveMove id="7352" type="1" pos="450,0,0" skillId="2150" distance="0.000000" randomRange="0.000000"/>
	<ActiveMove id="7353" type="1" pos="450,0,0" skillId="1150" distance="0.000000" randomRange="0.000000"/>
	<ActiveMove id="7354" type="1" pos="450,0,0" skillId="2150" distance="0.000000" randomRange="0.000000"/>
	<ActiveMove id="7355" type="5" distance="100.000000" randomRange="200.000000" skillId="1150"/>
	<ActiveMove id="7356" type="5" distance="100.000000" randomRange="200.000000" skillId="2150"/>
	<ActiveMove id="7357" type="1" pos="450,0,0" skillId="1150" distance="0.000000" randomRange="0.000000"/>
	<ActiveMove id="7358" type="1" pos="450,0,0" skillId="2150" distance="0.000000" randomRange="0.000000"/>
	<ActiveMove id="7359" type="1" pos="450,0,0" skillId="1150" distance="0.000000" randomRange="0.000000"/>
	<ActiveMove id="7360" type="1" pos="450,0,0" skillId="2150" distance="0.000000" randomRange="0.000000"/>
	<ActiveMove id="7361" type="5" distance="100.000000" randomRange="200.000000" skillId="1150"/>
	<ActiveMove id="7362" type="5" distance="100.000000" randomRange="200.000000" skillId="2150"/>
	<ActiveMove id="7363" type="1" pos="450,0,0" skillId="1150" distance="0.000000" randomRange="0.000000"/>
	<ActiveMove id="7364" type="1" pos="450,0,0" skillId="2150" distance="0.000000" randomRange="0.000000"/>
	<ActiveMove id="7365" type="1" pos="450,0,0" skillId="1150" distance="0.000000" randomRange="0.000000"/>
	<ActiveMove id="7366" type="1" pos="450,0,0" skillId="2150" distance="0.000000" randomRange="0.000000"/>
	<ActiveMove id="7367" type="5" distance="100.000000" randomRange="200.000000" skillId="1150"/>
	<ActiveMove id="7368" type="5" distance="100.000000" randomRange="200.000000" skillId="2150"/>
	<ActiveMove id="7369" type="1" pos="450,0,0" skillId="1150" distance="0.000000" randomRange="0.000000"/>
	<ActiveMove id="7370" type="1" pos="450,0,0" skillId="2150" distance="0.000000" randomRange="0.000000"/>
	<ActiveMove id="7371" type="1" pos="450,0,0" skillId="1150" distance="0.000000" randomRange="0.000000"/>
	<ActiveMove id="7372" type="1" pos="450,0,0" skillId="2150" distance="0.000000" randomRange="0.000000"/>
	<ActiveMove id="7373" type="5" distance="100.000000" randomRange="200.000000" skillId="1150"/>
	<ActiveMove id="7374" type="5" distance="100.000000" randomRange="200.000000" skillId="2150"/>
	<ActiveMove id="7375" type="1" pos="450,0,0" skillId="1150" distance="0.000000" randomRange="0.000000"/>
	<ActiveMove id="7376" type="1" pos="450,0,0" skillId="2150" distance="0.000000" randomRange="0.000000"/>
	<ActiveMove id="7377" type="1" pos="450,0,0" skillId="1150" distance="0.000000" randomRange="0.000000"/>
	<ActiveMove id="7378" type="1" pos="450,0,0" skillId="2150" distance="0.000000" randomRange="0.000000"/>
	<ActiveMove id="7379" type="5" distance="100.000000" randomRange="200.000000" skillId="1150"/>
	<ActiveMove id="7380" type="5" distance="100.000000" randomRange="200.000000" skillId="2150"/>
	<ActiveMove id="7381" type="1" pos="450,0,0" skillId="1150" distance="0.000000" randomRange="0.000000"/>
	<ActiveMove id="7382" type="1" pos="450,0,0" skillId="2150" distance="0.000000" randomRange="0.000000"/>
	<ActiveMove id="7383" type="1" pos="450,0,0" skillId="1150" distance="0.000000" randomRange="0.000000"/>
	<ActiveMove id="7384" type="1" pos="450,0,0" skillId="2150" distance="0.000000" randomRange="0.000000"/>
	<ActiveMove id="7385" type="5" distance="100.000000" randomRange="200.000000" skillId="1150"/>
	<ActiveMove id="7386" type="5" distance="100.000000" randomRange="200.000000" skillId="2150"/>
	<ActiveMove id="7387" type="1" pos="450,0,0" skillId="1150" distance="0.000000" randomRange="0.000000"/>
	<ActiveMove id="7388" type="1" pos="450,0,0" skillId="2150" distance="0.000000" randomRange="0.000000"/>
	<ActiveMove id="7389" type="5" distance="200.000000" randomRange="0.000000" skillId="1150"/>
	<ActiveMove id="7390" type="5" distance="200.000000" randomRange="0.000000" skillId="2150"/>
	<ActiveMove id="7391" type="1" pos="450,0,0" skillId="1150" distance="0.000000" randomRange="0.000000"/>
	<ActiveMove id="7392" type="1" pos="450,0,0" skillId="2150" distance="0.000000" randomRange="0.000000"/>
	<ActiveMove id="7393" type="5" distance="200.000000" randomRange="0.000000" skillId="1150"/>
	<ActiveMove id="7394" type="5" distance="200.000000" randomRange="0.000000" skillId="2150"/>
	<ActiveMove id="7395" type="1" pos="450,0,0" skillId="1150" distance="0.000000" randomRange="0.000000"/>
	<ActiveMove id="7396" type="1" pos="450,0,0" skillId="2150" distance="0.000000" randomRange="0.000000"/>
	<ActiveMove id="7397" type="5" distance="200.000000" randomRange="0.000000" skillId="1150"/>
	<ActiveMove id="7398" type="5" distance="200.000000" randomRange="0.000000" skillId="2150"/>
	<ActiveMove id="7399" type="1" pos="450,0,0" skillId="1150" distance="0.000000" randomRange="0.000000"/>
	<ActiveMove id="7400" type="1" pos="450,0,0" skillId="2150" distance="0.000000" randomRange="0.000000"/>
	<ActiveMove id="7401" type="5" distance="200.000000" randomRange="0.000000" skillId="1150"/>
	<ActiveMove id="7402" type="5" distance="200.000000" randomRange="0.000000" skillId="2150"/>
	<ActiveMove id="7403" type="1" pos="450,0,0" skillId="1150" distance="0.000000" randomRange="0.000000"/>
	<ActiveMove id="7404" type="1" pos="450,0,0" skillId="2150" distance="0.000000" randomRange="0.000000"/>
	<ActiveMove id="7405" type="5" distance="200.000000" randomRange="0.000000" skillId="1150"/>
	<ActiveMove id="7406" type="5" distance="200.000000" randomRange="0.000000" skillId="2150"/>
	<ActiveMove id="7407" type="1" pos="450,0,0" skillId="1150" distance="0.000000" randomRange="0.000000"/>
	<ActiveMove id="7408" type="1" pos="450,0,0" skillId="2150" distance="0.000000" randomRange="0.000000"/>
	<ActiveMove id="7409" type="5" distance="200.000000" randomRange="0.000000" skillId="1150"/>
	<ActiveMove id="7410" type="5" distance="200.000000" randomRange="0.000000" skillId="2150"/>
	<ActiveMove id="7411" type="1" pos="450,0,0" skillId="1150" distance="0.000000" randomRange="0.000000"/>
	<ActiveMove id="7412" type="1" pos="450,0,0" skillId="2150" distance="0.000000" randomRange="0.000000"/>
	<ActiveMove id="7413" type="5" distance="200.000000" randomRange="0.000000" skillId="1150"/>
	<ActiveMove id="7414" type="5" distance="200.000000" randomRange="0.000000" skillId="2150"/>
	<ActiveMove id="7415" type="1" pos="450,0,0" skillId="1150" distance="0.000000" randomRange="0.000000"/>
	<ActiveMove id="7416" type="1" pos="450,0,0" skillId="2150" distance="0.000000" randomRange="0.000000"/>
	<ActiveMove id="7417" type="5" distance="200.000000" randomRange="0.000000" skillId="1150"/>
	<ActiveMove id="7418" type="5" distance="200.000000" randomRange="0.000000" skillId="2150"/>
	<ActiveMove id="7419" type="1" pos="450,0,0" skillId="1150" distance="0.000000" randomRange="0.000000"/>
	<ActiveMove id="7420" type="1" pos="450,0,0" skillId="2150" distance="0.000000" randomRange="0.000000"/>
	<ActiveMove id="7421" type="1" pos="450,0,0" skillId="1150" distance="0.000000" randomRange="0.000000"/>
	<ActiveMove id="7422" type="1" pos="450,0,0" skillId="2150" distance="0.000000" randomRange="0.000000"/>
	<ActiveMove id="7423" type="5" distance="100.000000" randomRange="200.000000" skillId="1150"/>
	<ActiveMove id="7424" type="5" distance="100.000000" randomRange="200.000000" skillId="2150"/>
	<ActiveMove id="7425" type="1" pos="450,0,0" skillId="1150" distance="0.000000" randomRange="0.000000"/>
	<ActiveMove id="7426" type="1" pos="450,0,0" skillId="2150" distance="0.000000" randomRange="0.000000"/>
	<ActiveMove id="7427" type="1" pos="450,0,0" skillId="1150" distance="0.000000" randomRange="0.000000"/>
	<ActiveMove id="7428" type="1" pos="450,0,0" skillId="2150" distance="0.000000" randomRange="0.000000"/>
	<ActiveMove id="7429" type="5" distance="100.000000" randomRange="200.000000" skillId="1150"/>
	<ActiveMove id="7430" type="5" distance="100.000000" randomRange="200.000000" skillId="2150"/>
	<ActiveMove id="7431" type="1" pos="450,0,0" skillId="1150" distance="0.000000" randomRange="0.000000"/>
	<ActiveMove id="7432" type="1" pos="450,0,0" skillId="2150" distance="0.000000" randomRange="0.000000"/>
	<ActiveMove id="7433" type="1" pos="450,0,0" skillId="1150" distance="0.000000" randomRange="0.000000"/>
	<ActiveMove id="7434" type="1" pos="450,0,0" skillId="2150" distance="0.000000" randomRange="0.000000"/>
	<ActiveMove id="7435" type="5" distance="100.000000" randomRange="200.000000" skillId="1150"/>
	<ActiveMove id="7436" type="5" distance="100.000000" randomRange="200.000000" skillId="2150"/>
	<ActiveMove id="7437" type="1" pos="450,0,0" skillId="1150" distance="0.000000" randomRange="0.000000"/>
	<ActiveMove id="7438" type="1" pos="450,0,0" skillId="2150" distance="0.000000" randomRange="0.000000"/>
	<ActiveMove id="7439" type="1" pos="450,0,0" skillId="1150" distance="0.000000" randomRange="0.000000"/>
	<ActiveMove id="7440" type="1" pos="450,0,0" skillId="2150" distance="0.000000" randomRange="0.000000"/>
	<ActiveMove id="7441" type="5" distance="100.000000" randomRange="200.000000" skillId="1150"/>
	<ActiveMove id="7442" type="5" distance="100.000000" randomRange="200.000000" skillId="2150"/>
	<ActiveMove id="7443" type="1" pos="450,0,0" skillId="1150" distance="0.000000" randomRange="0.000000"/>
	<ActiveMove id="7444" type="1" pos="450,0,0" skillId="2150" distance="0.000000" randomRange="0.000000"/>
	<ActiveMove id="7445" type="1" pos="450,0,0" skillId="1150" distance="0.000000" randomRange="0.000000"/>
	<ActiveMove id="7446" type="1" pos="450,0,0" skillId="2150" distance="0.000000" randomRange="0.000000"/>
	<ActiveMove id="7447" type="5" distance="100.000000" randomRange="200.000000" skillId="1150"/>
	<ActiveMove id="7448" type="5" distance="100.000000" randomRange="200.000000" skillId="2150"/>
	<ActiveMove id="7449" type="1" pos="450,0,0" skillId="1150" distance="0.000000" randomRange="0.000000"/>
	<ActiveMove id="7450" type="1" pos="450,0,0" skillId="2150" distance="0.000000" randomRange="0.000000"/>
	<ActiveMove id="7451" type="1" pos="450,0,0" skillId="1150" distance="0.000000" randomRange="0.000000"/>
	<ActiveMove id="7452" type="1" pos="450,0,0" skillId="2150" distance="0.000000" randomRange="0.000000"/>
	<ActiveMove id="7453" type="5" distance="100.000000" randomRange="200.000000" skillId="1150"/>
	<ActiveMove id="7454" type="5" distance="100.000000" randomRange="200.000000" skillId="2150"/>
	<ActiveMove id="7455" type="1" pos="450,0,0" skillId="1150" distance="0.000000" randomRange="0.000000"/>
	<ActiveMove id="7456" type="1" pos="450,0,0" skillId="2150" distance="0.000000" randomRange="0.000000"/>
	<ActiveMove id="7457" type="1" pos="450,0,0" skillId="1150" distance="0.000000" randomRange="0.000000"/>
	<ActiveMove id="7458" type="1" pos="450,0,0" skillId="2150" distance="0.000000" randomRange="0.000000"/>
	<ActiveMove id="7459" type="5" distance="100.000000" randomRange="200.000000" skillId="1150"/>
	<ActiveMove id="7460" type="5" distance="100.000000" randomRange="200.000000" skillId="2150"/>
	<ActiveMove id="7461" type="1" pos="450,0,0" skillId="1150" distance="0.000000" randomRange="0.000000"/>
	<ActiveMove id="7462" type="1" pos="450,0,0" skillId="2150" distance="0.000000" randomRange="0.000000"/>
	<ActiveMove id="7463" type="1" pos="450,0,0" skillId="1150" distance="0.000000" randomRange="0.000000"/>
	<ActiveMove id="7464" type="1" pos="450,0,0" skillId="2150" distance="0.000000" randomRange="0.000000"/>
	<ActiveMove id="7465" type="5" distance="100.000000" randomRange="200.000000" skillId="1150"/>
	<ActiveMove id="7466" type="5" distance="100.000000" randomRange="200.000000" skillId="2150"/>
	<ActiveMove id="7467" type="1" pos="450,0,0" skillId="1150" distance="0.000000" randomRange="0.000000"/>
	<ActiveMove id="7468" type="1" pos="450,0,0" skillId="2150" distance="0.000000" randomRange="0.000000"/>
	<ActiveMove id="7469" type="5" distance="200.000000" randomRange="0.000000" skillId="1150"/>
	<ActiveMove id="7470" type="5" distance="200.000000" randomRange="0.000000" skillId="2150"/>
	<ActiveMove id="7471" type="1" pos="450,0,0" skillId="1150" distance="0.000000" randomRange="0.000000"/>
	<ActiveMove id="7472" type="1" pos="450,0,0" skillId="2150" distance="0.000000" randomRange="0.000000"/>
	<ActiveMove id="7473" type="5" distance="200.000000" randomRange="0.000000" skillId="1150"/>
	<ActiveMove id="7474" type="5" distance="200.000000" randomRange="0.000000" skillId="2150"/>
	<ActiveMove id="7475" type="1" pos="-400.0000,0.0000,0.0000" skillId="0" distance="0.000000" randomRange="0.000000"/>
	<ActiveMove id="7476" type="3" pos="0.0000,-1.0000,0.0000" skillId="0" distance="200.000000" randomRange="10.000000"/>
</ActiveMoveTemplate>
