<?xml version="1.0" encoding="utf-8"?>
<DefaultSkillSet>
	<Default race="Human" gender="Male" class="Warrior" activeSkillIdList="10100;20100;9020100;60401301" passiveSkillIdList="10001;19100;19101;19102" />
	<Default race="Human" gender="Male" class="Lancer" activeSkillIdList="10100;20100;9020100;260100;60401301" passiveSkillIdList="10000;19100;19101;19102" />
	<Default race="Human" gender="Male" class="Slayer" activeSkillIdList="10100;40100;9020100;60401301" passiveSkillIdList="10002;19100;19101;19102" />
	<Default race="Human" gender="Male" class="Berserker" activeSkillIdList="10100;20100;290100;9020100;60401301" passiveSkillIdList="10000;19100;19101;19102;14070" />
	<Default race="Human" gender="Male" class="Sorcerer" activeSkillIdList="10100;70100;9020100;60401301" passiveSkillIdList="10002;19100;19101;19102" />
	<Default race="Human" gender="Male" class="Archer" activeSkillIdList="10100;60100;9020100;60401301" passiveSkillIdList="10002;19100;19101;19102" />
	<Default race="Human" gender="Male" class="Priest" activeSkillIdList="10100;180100;9020100;380100;60401301" passiveSkillIdList="10002;19100;19101;19102" />
	<Default race="Human" gender="Male" class="Elementalist" activeSkillIdList="10100;170100;180100;9020100;60401301" passiveSkillIdList="10002;19100;19101;19102" />
	<Default race="Human" gender="Male" class="Fighter" activeSkillIdList="10100;20100;400100;9020100;60401301" passiveSkillIdList="10002;19100;19101;19102;92001;92002;92003;92004;92005;92006;92007;92008;92009;92010;92011;92012" />
	<Default race="Human" gender="Female" class="Warrior" activeSkillIdList="10100;20100;9020100;60401301" passiveSkillIdList="10001;19100;19101;19102" />
	<Default race="Human" gender="Female" class="Lancer" activeSkillIdList="10100;20100;9020100;260100;60401301" passiveSkillIdList="10000;19100;19101;19102" />
	<Default race="Human" gender="Female" class="Slayer" activeSkillIdList="10100;40100;9020100;60401301" passiveSkillIdList="10002;19100;19101;19102" />
	<Default race="Human" gender="Female" class="Berserker" activeSkillIdList="10100;20100;290100;9020100;60401301" passiveSkillIdList="10000;19100;19101;19102;14070" />
	<Default race="Human" gender="Female" class="Sorcerer" activeSkillIdList="10100;70100;9020100;60401301" passiveSkillIdList="10002;19100;19101;19102" />
	<Default race="Human" gender="Female" class="Archer" activeSkillIdList="10100;60100;9020100;60401301" passiveSkillIdList="10002;19100;19101;19102" />
	<Default race="Human" gender="Female" class="Priest" activeSkillIdList="10100;180100;9020100;380100;60401301" passiveSkillIdList="10002;19100;19101;19102" />
	<Default race="Human" gender="Female" class="Elementalist" activeSkillIdList="10100;170100;180100;9020100;60401301" passiveSkillIdList="10002;19100;19101;19102" />
	<Default race="Human" gender="Female" class="Fighter" activeSkillIdList="10100;20100;400100;9020100;60401301" passiveSkillIdList="10002;19100;19101;19102;92001;92002;92003;92004;92005;92006;92007;92008;92009;92010;92011;92012" />
	<Default race="Highelf" gender="Male" class="Warrior" activeSkillIdList="10100;20100;9020100;60401301" passiveSkillIdList="10001;19200;19201" />
	<Default race="Highelf" gender="Male" class="Lancer" activeSkillIdList="10100;20100;9020100;260100;60401301" passiveSkillIdList="10000;19200;19201" />
	<Default race="Highelf" gender="Male" class="Slayer" activeSkillIdList="10100;40100;9020100;60401301" passiveSkillIdList="10002;19200;19201" />
	<Default race="Highelf" gender="Male" class="Berserker" activeSkillIdList="10100;20100;290100;9020100;60401301" passiveSkillIdList="10000;19200;19201;14070" />
	<Default race="Highelf" gender="Male" class="Sorcerer" activeSkillIdList="10100;70100;9020100;60401301" passiveSkillIdList="10000;19200;19201;14070" />
	<Default race="Highelf" gender="Male" class="Archer" activeSkillIdList="10100;60100;9020100;60401301" passiveSkillIdList="10002;19200;19201" />
	<Default race="Highelf" gender="Male" class="Priest" activeSkillIdList="10100;180100;9020100;380100;60401301" passiveSkillIdList="10002;19200;19201" />
	<Default race="Highelf" gender="Male" class="Elementalist" activeSkillIdList="10100;170100;180100;9020100;60401301" passiveSkillIdList="10002;19200;19201" />
	<Default race="Highelf" gender="Female" class="Warrior" activeSkillIdList="10100;20100;9020100;60401301" passiveSkillIdList="10001;19200;19201" />
	<Default race="Highelf" gender="Female" class="Lancer" activeSkillIdList="10100;20100;9020100;260100;60401301" passiveSkillIdList="10000;19200;19201" />
	<Default race="Highelf" gender="Female" class="Slayer" activeSkillIdList="10100;40100;9020100;60401301" passiveSkillIdList="10002;19200;19201" />
	<Default race="Highelf" gender="Female" class="Berserker" activeSkillIdList="10100;20100;290100;9020100;60401301" passiveSkillIdList="10000;19200;19201;14070" />
	<Default race="Highelf" gender="Female" class="Sorcerer" activeSkillIdList="10100;70100;9020100;60401301" passiveSkillIdList="10002;19200;19201" />
	<Default race="Highelf" gender="Female" class="Archer" activeSkillIdList="10100;60100;9020100;60401301" passiveSkillIdList="10002;19200;19201" />
	<Default race="Highelf" gender="Female" class="Priest" activeSkillIdList="10100;180100;9020100;380100;60401301" passiveSkillIdList="10002;19200;19201" />
	<Default race="Highelf" gender="Female" class="Elementalist" activeSkillIdList="10100;170100;180100;9020100;60401301" passiveSkillIdList="10002;19200;19201" />
	<Default race="Highelf" gender="Female" class="Engineer" activeSkillIdList="10100;400100;9020100;60401301" passiveSkillIdList="10003;19200;19201;91013;91014;91003;91004;91006" />
	<Default race="Aman" gender="Male" class="Warrior" activeSkillIdList="10100;20100;9020100;60401301" passiveSkillIdList="10001;19400;19401;19402" />
	<Default race="Aman" gender="Male" class="Lancer" activeSkillIdList="10100;20100;9020100;260100;60401301" passiveSkillIdList="10000;19400;19401;19402" />
	<Default race="Aman" gender="Male" class="Slayer" activeSkillIdList="10100;40100;9020100;60401301" passiveSkillIdList="10002;19400;19401;19402" />
	<Default race="Aman" gender="Male" class="Berserker" activeSkillIdList="10100;20100;290100;9020100;60401301" passiveSkillIdList="10000;19400;19401;19402;14070" />
	<Default race="Aman" gender="Male" class="Sorcerer" activeSkillIdList="10100;70100;9020100;60401301" passiveSkillIdList="10002;19400;19401;19402" />
	<Default race="Aman" gender="Male" class="Archer" activeSkillIdList="10100;60100;9020100;60401301" passiveSkillIdList="10002;19400;19401;19402" />
	<Default race="Aman" gender="Male" class="Priest" activeSkillIdList="10100;180100;9020100;380100;60401301" passiveSkillIdList="10002;19400;19401;19402" />
	<Default race="Aman" gender="Male" class="Elementalist" activeSkillIdList="10100;170100;180100;9020100;60401301" passiveSkillIdList="10002;19400;19401;19402" />
	<Default race="Aman" gender="Female" class="Warrior" activeSkillIdList="10100;20100;9020100;60401301" passiveSkillIdList="10001;19400;19401;19402" />
	<Default race="Aman" gender="Female" class="Lancer" activeSkillIdList="10100;20100;9020100;260100;60401301" passiveSkillIdList="10000;19400;19401;19402" />
	<Default race="Aman" gender="Female" class="Slayer" activeSkillIdList="10100;40100;9020100;60401301" passiveSkillIdList="10002;19400;19401;19402" />
	<Default race="Aman" gender="Female" class="Berserker" activeSkillIdList="10100;20100;290100;9020100;60401301" passiveSkillIdList="10000;19400;19401;19402;14070" />
	<Default race="Aman" gender="Female" class="Sorcerer" activeSkillIdList="10100;70100;9020100;60401301" passiveSkillIdList="10002;19400;19401;19402" />
	<Default race="Aman" gender="Female" class="Archer" activeSkillIdList="10100;60100;9020100;60401301" passiveSkillIdList="10002;19400;19401;19402" />
	<Default race="Aman" gender="Female" class="Priest" activeSkillIdList="10100;180100;9020100;380100;60401301" passiveSkillIdList="10002;19400;19401;19402" />
	<Default race="Aman" gender="Female" class="Elementalist" activeSkillIdList="10100;170100;180100;9020100;60401301" passiveSkillIdList="10002;19400;19401;19402" />
	<Default race="Castanic" gender="Male" class="Warrior" activeSkillIdList="10100;20100;9020100;60401301" passiveSkillIdList="10001;19300;19301;19302" />
	<Default race="Castanic" gender="Male" class="Lancer" activeSkillIdList="10100;20100;9020100;260100;60401301" passiveSkillIdList="10000;19300;19301;19302" />
	<Default race="Castanic" gender="Male" class="Slayer" activeSkillIdList="10100;40100;9020100;60401301" passiveSkillIdList="10002;19300;19301;19302" />
	<Default race="Castanic" gender="Male" class="Berserker" activeSkillIdList="10100;20100;290100;9020100;60401301" passiveSkillIdList="10000;19300;19301;19302;14070" />
	<Default race="Castanic" gender="Male" class="Sorcerer" activeSkillIdList="10100;70100;9020100;60401301" passiveSkillIdList="10002;19300;19301;19302" />
	<Default race="Castanic" gender="Male" class="Archer" activeSkillIdList="10100;60100;9020100;60401301" passiveSkillIdList="10002;19300;19301;19302" />
	<Default race="Castanic" gender="Male" class="Priest" activeSkillIdList="10100;180100;9020100;380100;60401301" passiveSkillIdList="10002;19300;19301;19302" />
	<Default race="Castanic" gender="Male" class="Elementalist" activeSkillIdList="10100;170100;180100;9020100;60401301" passiveSkillIdList="10002;19300;19301;19302" />
	<Default race="Castanic" gender="Female" class="Warrior" activeSkillIdList="10100;20100;9020100;60401301" passiveSkillIdList="10001;19300;19301;19302" />
	<Default race="Castanic" gender="Female" class="Lancer" activeSkillIdList="10100;20100;9020100;260100;60401301" passiveSkillIdList="10000;19300;19301;19302" />
	<Default race="Castanic" gender="Female" class="Slayer" activeSkillIdList="10100;40100;9020100;60401301" passiveSkillIdList="10002;19300;19301;19302" />
	<Default race="Castanic" gender="Female" class="Berserker" activeSkillIdList="10100;20100;290100;9020100;60401301" passiveSkillIdList="10000;19300;19301;19302;14070" />
	<Default race="Castanic" gender="Female" class="Sorcerer" activeSkillIdList="10100;70100;9020100;60401301" passiveSkillIdList="10002;19300;19301;19302" />
	<Default race="Castanic" gender="Female" class="Archer" activeSkillIdList="10100;60100;9020100;60401301" passiveSkillIdList="10002;19300;19301;19302" />
	<Default race="Castanic" gender="Female" class="Priest" activeSkillIdList="10100;180100;9020100;380100;60401301" passiveSkillIdList="10002;19300;19301;19302" />
	<Default race="Castanic" gender="Female" class="Elementalist" activeSkillIdList="10100;170100;180100;9020100;60401301" passiveSkillIdList="10002;19300;19301;19302" />
	<Default race="Castanic" gender="Female" class="Engineer" activeSkillIdList="10100;400100;9020100;60401301" passiveSkillIdList="10003;19300;19301;19302;91013;91014;91003;91004;91006" />
	<Default race="Castanic" gender="Female" class="Glaiver" activeSkillIdList="10199;60199;140199;160199;9020100;60401301" passiveSkillIdList="10002;19300;19301;19302;94001;94002;94003;94005;94006;94007;94008;94009;94010;94011;94012;94013;94014;94015" />
	<Default race="Popori" gender="Male" class="Warrior" activeSkillIdList="10100;20100;9020100;9030100;60401301" passiveSkillIdList="10001;19500;19501" />
	<Default race="Popori" gender="Male" class="Lancer" activeSkillIdList="10100;20100;9020100;9030100;260100;60401301" passiveSkillIdList="10000;19500;19501" />
	<Default race="Popori" gender="Male" class="Slayer" activeSkillIdList="10100;40100;9020100;9030100;60401301" passiveSkillIdList="10002;19500;19501" />
	<Default race="Popori" gender="Male" class="Berserker" activeSkillIdList="10100;20100;290100;9020100;9030100;60401301" passiveSkillIdList="10000;19500;19501;14070" />
	<Default race="Popori" gender="Male" class="Sorcerer" activeSkillIdList="10100;70100;9020100;9030100;60401301" passiveSkillIdList="10002;19500;19501" />
	<Default race="Popori" gender="Male" class="Archer" activeSkillIdList="10100;60100;9020100;9030100;60401301" passiveSkillIdList="10002;19500;19501" />
	<Default race="Popori" gender="Male" class="Priest" activeSkillIdList="10100;180100;9020100;9030100;380100;60401301" passiveSkillIdList="10002;19500;19501" />
	<Default race="Popori" gender="Male" class="Elementalist" activeSkillIdList="10100;170100;180100;9020100;9030100;60401301" passiveSkillIdList="10002;19500;19501" />
	<Default race="Popori" gender="Male" class="Fighter" activeSkillIdList="10100;20100;400100;9020100;9030100;60401301" passiveSkillIdList="10002;19500;19501;92001;92002;92003;92004;92005;92006;92007;92008;92009;92010;92011;92012" />
	<Default race="Popori" gender="Female" class="Warrior" activeSkillIdList="10100;20100;9020100;9030100;60401301" passiveSkillIdList="10001;19500;19501" />
	<Default race="Popori" gender="Female" class="Lancer" activeSkillIdList="10100;20100;9020100;9030100;260100;60401301" passiveSkillIdList="10000;19500;19501" />
	<Default race="Popori" gender="Female" class="Slayer" activeSkillIdList="10100;40100;9020100;9030100;60401301" passiveSkillIdList="10002;19500;19501" />
	<Default race="Popori" gender="Female" class="Berserker" activeSkillIdList="10100;20100;290100;9020100;9030100;60401301" passiveSkillIdList="10000;19500;19501;14070" />
	<Default race="Popori" gender="Female" class="Sorcerer" activeSkillIdList="10100;70100;9020100;9030100;60401301" passiveSkillIdList="10002;19500;19501" />
	<Default race="Popori" gender="Female" class="Archer" activeSkillIdList="10100;60100;9020100;9030100;60401301" passiveSkillIdList="10002;19500;19501" />
	<Default race="Popori" gender="Female" class="Priest" activeSkillIdList="10100;180100;9020100;9030100;380100;60401301" passiveSkillIdList="10002;19500;19501" />
	<Default race="Popori" gender="Female" class="Elementalist" activeSkillIdList="10100;170100;180100;9020100;9030100;60401301" passiveSkillIdList="10002;19500;19501" />
	<Default race="Popori" gender="Female" class="Soulless" activeSkillIdList="10100;30100;140100;150100;400100;9020100;9030100;111111;60401301" passiveSkillIdList="10001;19500;19501;90001" />
	<Default race="Popori" gender="Female" class="Assassin" activeSkillIdList="10100;20100;70100;9020100;9030100;60401301" passiveSkillIdList="10002;19500;19501;93001;93002;93003;93004;93005;93006;93008" />
	<Default race="Popori" gender="Female" class="Engineer" activeSkillIdList="10100;400100;9020100;9030100;60401301" passiveSkillIdList="10003;19500;19501;91013;91014;91003;91004;91006" />
	<Default race="Popori" gender="Female" class="Fighter" activeSkillIdList="10100;20100;400100;9020100;9030100;60401301" passiveSkillIdList="10002;19500;19501;92001;92002;92003;92004;92005;92006;92007;92008;92009;92010;92011;92012" />
	<Default race="Popori" gender="Female" class="Glaiver" activeSkillIdList="10199;60199;140199;160199;9020100;9030100;60401301" passiveSkillIdList="10002;19500;19501;94001;94002;94003;94005;94006;94007;94008;94009;94010;94011;94012;94013;94014;94015" />
	<Default race="Baraka" gender="Male" class="Warrior" activeSkillIdList="10100;20100;9020100;60401301" passiveSkillIdList="10001;19601;19602" />
	<Default race="Baraka" gender="Male" class="Lancer" activeSkillIdList="10100;20100;9020100;260100;60401301" passiveSkillIdList="10000;19601;19602" />
	<Default race="Baraka" gender="Male" class="Slayer" activeSkillIdList="10100;40100;9020100;60401301" passiveSkillIdList="10002;19601;19602" />
	<Default race="Baraka" gender="Male" class="Berserker" activeSkillIdList="10100;20100;290100;9020100;60401301" passiveSkillIdList="10000;19601;19602;14070" />
	<Default race="Baraka" gender="Male" class="Sorcerer" activeSkillIdList="10100;70100;9020100;60401301" passiveSkillIdList="10002;19601;19602" />
	<Default race="Baraka" gender="Male" class="Archer" activeSkillIdList="10100;60100;9020100;60401301" passiveSkillIdList="10002;19601;19602" />
	<Default race="Baraka" gender="Male" class="Priest" activeSkillIdList="10100;180100;9020100;380100;60401301" passiveSkillIdList="10002;19601;19602" />
	<Default race="Baraka" gender="Male" class="Elementalist" activeSkillIdList="10100;170100;180100;9020100;60401301" passiveSkillIdList="10002;19601;19602" />
</DefaultSkillSet>